Ice40/Modulos/Pulso/Tics/gtkwave/Full Detector/FallingRisingChange_M2_test.v
// Code generated by Icestudio 0.3.3
// Mon, 03 Dec 2018 00:20:25 GMT

`default_nettype none

module main (
 input v08bfd6,
 input v02d455,
 output vdbb75f,
 output v317e8f,
 output v32443d,
 output [0:4] vinit
);
 wire w0;
 wire w1;
 wire w2;
 wire w3;
 wire w4;
 assign vdbb75f = w0;
 assign v317e8f = w1;
 assign v32443d = w2;
 assign w3 = v08bfd6;
 assign w4 = v02d455;
 vf67014 v434f99 (
  .vdbb75f(w0),
  .v317e8f(w1),
  .v32443d(w2),
  .v08bfd6(w3),
  .v02d455(w4)
 );
 assign vinit = 5'b00000;
endmodule

module vf67014 (
 input v08bfd6,
 input v02d455,
 output vdbb75f,
 output v317e8f,
 output v32443d
);
 wire w0;
 wire w1;
 wire w2;
 wire w3;
 wire w4;
 assign vdbb75f = w0;
 assign v317e8f = w1;
 assign v32443d = w2;
 assign w3 = v08bfd6;
 assign w4 = v02d455;
 vf67014_v3523b6 v3523b6 (
  .Toggle(w0),
  .Falling(w1),
  .Rising(w2),
  .in(w3),
  .clk(w4)
 );
endmodule

module vf67014_v3523b6 (
 input in,
 input clk,
 output Toggle,
 output Falling,
 output Rising
);
 
 reg Q1=0,Q2=0;
 
 //Biestable D donde capturo estado actual (in) y anterior (Q)
 always @(posedge clk)
 begin
   Q1<=in;
   Q2<=Q1;
 end
 
 //Con datos del estado actual ya anterior, realizando un circutio combinacional
 //puedo saber si la señal a cambiado y si ha subido o ha bajado el flanco.
 
 assign Toggle= (Q2 ^ in); //Si son distintos es que hay un cambio
 assign Falling = (~in & Q2); // Si in (Actual) es 0 pero antes (Q) era 1 -->Falling
 assign Rising  = (in & ~Q2); // Si in (Actual) es 1 pero antes (Q) era 0 --> Rising
endmodule

Ice40/Modulos/Pulso/Tics/gtkwave/Full Detector/FallingRisingChange_M2_test_tb.v
// Code generated by Icestudio 0.3.3
// Mon, 03 Dec 2018 00:20:36 GMT

// Testbench template

`default_nettype none
`define DUMPSTR(x) `"x.vcd`"
`timescale 10 ns / 1 ns


module main_tb
;
 
 // Simulation time: 100ns (10 * 10ns)
 parameter DURATION = 100;
 
 // Input/Output
 reg in;
 reg clk;
 wire T;
 wire F;
 wire R;
 
 // Module instance
 main MAIN (
  .v08bfd6(in),
  .v02d455(clk),
  .vdbb75f(T),
  .v317e8f(F),
  .v32443d(R)
 );
 
 // Clock signal
 always #0.5 clk = ~clk;
 
 initial begin
  // File were to store the simulation results
  $dumpfile(`DUMPSTR(`VCD_OUTPUT));
  $dumpvars(0, main_tb);
 
  // TODO: initialize the registers here
  // e.g. value = 1;
  // e.g. #2 value = 0;
  in = 0;
  clk = 1;
  #4 in=1;
  #6 in=0;
  #3 in=1;
  #7 in=0;
  #4 in=1;
  #1 in=0;
  #2 in=1;
  #7 in=0;
  
 
  #(DURATION) $display("End of simulation");
  $finish;
 end
 
endmodule

Ice40/Modulos/Pulso/Tics/gtkwave/Full Detector/FallingRisingChange_M2_test_tb.vcd
$date
	Mon Dec 03 01:22:02 2018
$end
$version
	Icarus Verilog
$end
$timescale
	1ns
$end
$scope module main_tb $end
$var wire 1 ! T $end
$var wire 1 " R $end
$var wire 1 # F $end
$var reg 1 $ clk $end
$var reg 1 % in $end
$scope module MAIN $end
$var wire 1 $ v02d455 $end
$var wire 1 % v08bfd6 $end
$var wire 1 # v317e8f $end
$var wire 1 " v32443d $end
$var wire 1 ! vdbb75f $end
$var wire 5 & vinit [0:4] $end
$var wire 1 ' w3 $end
$var wire 1 ( w4 $end
$var wire 1 ) w2 $end
$var wire 1 * w1 $end
$var wire 1 + w0 $end
$scope module v434f99 $end
$var wire 1 ( v02d455 $end
$var wire 1 ' v08bfd6 $end
$var wire 1 * v317e8f $end
$var wire 1 ) v32443d $end
$var wire 1 + vdbb75f $end
$var wire 1 , w3 $end
$var wire 1 - w4 $end
$var wire 1 . w2 $end
$var wire 1 / w1 $end
$var wire 1 0 w0 $end
$scope module v3523b6 $end
$var wire 1 / Falling $end
$var wire 1 . Rising $end
$var wire 1 0 Toggle $end
$var wire 1 - clk $end
$var wire 1 , in $end
$var reg 1 1 Q1 $end
$var reg 1 2 Q2 $end
$upscope $end
$upscope $end
$upscope $end
$upscope $end
$enddefinitions $end
#0
$dumpvars
02
01
00
0/
0.
1-
0,
0+
0*
0)
1(
0'
b0 &
0%
1$
0#
0"
0!
$end
#5
0-
0(
0$
#10
1-
1(
1$
#15
0-
0(
0$
#20
1-
1(
1$
#25
0-
0(
0$
#30
1-
1(
1$
#35
0-
0(
0$
#40
11
1!
1+
10
1"
1)
1.
1-
1(
1$
1,
1'
1%
#45
0-
0(
0$
#50
0"
0)
0.
0!
0+
00
12
1-
1(
1$
#55
0-
0(
0$
#60
1-
1(
1$
#65
0-
0(
0$
#70
1-
1(
1$
#75
0-
0(
0$
#80
1-
1(
1$
#85
0-
0(
0$
#90
1-
1(
1$
#95
0-
0(
0$
#100
01
1#
1*
1/
1!
1+
10
1-
1(
1$
0,
0'
0%
#105
0-
0(
0$
#110
0#
0*
0/
0!
0+
00
02
1-
1(
1$
#115
0-
0(
0$
#120
1-
1(
1$
#125
0-
0(
0$
#130
11
1!
1+
10
1"
1)
1.
1-
1(
1$
1,
1'
1%
#135
0-
0(
0$
#140
0"
0)
0.
0!
0+
00
12
1-
1(
1$
#145
0-
0(
0$
#150
1-
1(
1$
#155
0-
0(
0$
#160
1-
1(
1$
#165
0-
0(
0$
#170
1-
1(
1$
#175
0-
0(
0$
#180
1-
1(
1$
#185
0-
0(
0$
#190
1-
1(
1$
#195
0-
0(
0$
#200
01
1#
1*
1/
1!
1+
10
1-
1(
1$
0,
0'
0%
#205
0-
0(
0$
#210
0#
0*
0/
0!
0+
00
02
1-
1(
1$
#215
0-
0(
0$
#220
1-
1(
1$
#225
0-
0(
0$
#230
1-
1(
1$
#235
0-
0(
0$
#240
11
1!
1+
10
1"
1)
1.
1-
1(
1$
1,
1'
1%
#245
0-
0(
0$
#250
1#
1*
1/
12
01
1!
1+
10
0"
0)
0.
1-
1(
1$
0,
0'
0%
#255
0-
0(
0$
#260
0#
0*
0/
0!
0+
00
02
1-
1(
1$
#265
0-
0(
0$
#270
11
1!
1+
10
1"
1)
1.
1-
1(
1$
1,
1'
1%
#275
0-
0(
0$
#280
0"
0)
0.
0!
0+
00
12
1-
1(
1$
#285
0-
0(
0$
#290
1-
1(
1$
#295
0-
0(
0$
#300
1-
1(
1$
#305
0-
0(
0$
#310
1-
1(
1$
#315
0-
0(
0$
#320
1-
1(
1$
#325
0-
0(
0$
#330
1-
1(
1$
#335
0-
0(
0$
#340
01
1#
1*
1/
1!
1+
10
1-
1(
1$
0,
0'
0%
#345
0-
0(
0$
#350
0#
0*
0/
0!
0+
00
02
1-
1(
1$
#355
0-
0(
0$
#360
1-
1(
1$
#365
0-
0(
0$
#370
1-
1(
1$
#375
0-
0(
0$
#380
1-
1(
1$
#385
0-
0(
0$
#390
1-
1(
1$
#395
0-
0(
0$
#400
1-
1(
1$
#405
0-
0(
0$
#410
1-
1(
1$
#415
0-
0(
0$
#420
1-
1(
1$
#425
0-
0(
0$
#430
1-
1(
1$
#435
0-
0(
0$
#440
1-
1(
1$
#445
0-
0(
0$
#450
1-
1(
1$
#455
0-
0(
0$
#460
1-
1(
1$
#465
0-
0(
0$
#470
1-
1(
1$
#475
0-
0(
0$
#480
1-
1(
1$
#485
0-
0(
0$
#490
1-
1(
1$
#495
0-
0(
0$
#500
1-
1(
1$
#505
0-
0(
0$
#510
1-
1(
1$
#515
0-
0(
0$
#520
1-
1(
1$
#525
0-
0(
0$
#530
1-
1(
1$
#535
0-
0(
0$
#540
1-
1(
1$
#545
0-
0(
0$
#550
1-
1(
1$
#555
0-
0(
0$
#560
1-
1(
1$
#565
0-
0(
0$
#570
1-
1(
1$
#575
0-
0(
0$
#580
1-
1(
1$
#585
0-
0(
0$
#590
1-
1(
1$
#595
0-
0(
0$
#600
1-
1(
1$
#605
0-
0(
0$
#610
1-
1(
1$
#615
0-
0(
0$
#620
1-
1(
1$
#625
0-
0(
0$
#630
1-
1(
1$
#635
0-
0(
0$
#640
1-
1(
1$
#645
0-
0(
0$
#650
1-
1(
1$
#655
0-
0(
0$
#660
1-
1(
1$
#665
0-
0(
0$
#670
1-
1(
1$
#675
0-
0(
0$
#680
1-
1(
1$
#685
0-
0(
0$
#690
1-
1(
1$
#695
0-
0(
0$
#700
1-
1(
1$
#705
0-
0(
0$
#710
1-
1(
1$
#715
0-
0(
0$
#720
1-
1(
1$
#725
0-
0(
0$
#730
1-
1(
1$
#735
0-
0(
0$
#740
1-
1(
1$
#745
0-
0(
0$
#750
1-
1(
1$
#755
0-
0(
0$
#760
1-
1(
1$
#765
0-
0(
0$
#770
1-
1(
1$
#775
0-
0(
0$
#780
1-
1(
1$
#785
0-
0(
0$
#790
1-
1(
1$
#795
0-
0(
0$
#800
1-
1(
1$
#805
0-
0(
0$
#810
1-
1(
1$
#815
0-
0(
0$
#820
1-
1(
1$
#825
0-
0(
0$
#830
1-
1(
1$
#835
0-
0(
0$
#840
1-
1(
1$
#845
0-
0(
0$
#850
1-
1(
1$
#855
0-
0(
0$
#860
1-
1(
1$
#865
0-
0(
0$
#870
1-
1(
1$
#875
0-
0(
0$
#880
1-
1(
1$
#885
0-
0(
0$
#890
1-
1(
1$
#895
0-
0(
0$
#900
1-
1(
1$
#905
0-
0(
0$
#910
1-
1(
1$
#915
0-
0(
0$
#920
1-
1(
1$
#925
0-
0(
0$
#930
1-
1(
1$
#935
0-
0(
0$
#940
1-
1(
1$
#945
0-
0(
0$
#950
1-
1(
1$
#955
0-
0(
0$
#960
1-
1(
1$
#965
0-
0(
0$
#970
1-
1(
1$
#975
0-
0(
0$
#980
1-
1(
1$
#985
0-
0(
0$
#990
1-
1(
1$
#995
0-
0(
0$
#1000
1-
1(
1$
#1005
0-
0(
0$
#1010
1-
1(
1$
#1015
0-
0(
0$
#1020
1-
1(
1$
#1025
0-
0(
0$
#1030
1-
1(
1$
#1035
0-
0(
0$
#1040
1-
1(
1$
#1045
0-
0(
0$
#1050
1-
1(
1$
#1055
0-
0(
0$
#1060
1-
1(
1$
#1065
0-
0(
0$
#1070
1-
1(
1$
#1075
0-
0(
0$
#1080
1-
1(
1$
#1085
0-
0(
0$
#1090
1-
1(
1$
#1095
0-
0(
0$
#1100
1-
1(
1$
#1105
0-
0(
0$
#1110
1-
1(
1$
#1115
0-
0(
0$
#1120
1-
1(
1$
#1125
0-
0(
0$
#1130
1-
1(
1$
#1135
0-
0(
0$
#1140
1-
1(
1$
#1145
0-
0(
0$
#1150
1-
1(
1$
#1155
0-
0(
0$
#1160
1-
1(
1$
#1165
0-
0(
0$
#1170
1-
1(
1$
#1175
0-
0(
0$
#1180
1-
1(
1$
#1185
0-
0(
0$
#1190
1-
1(
1$
#1195
0-
0(
0$
#1200
1-
1(
1$
#1205
0-
0(
0$
#1210
1-
1(
1$
#1215
0-
0(
0$
#1220
1-
1(
1$
#1225
0-
0(
0$
#1230
1-
1(
1$
#1235
0-
0(
0$
#1240
1-
1(
1$
#1245
0-
0(
0$
#1250
1-
1(
1$
#1255
0-
0(
0$
#1260
1-
1(
1$
#1265
0-
0(
0$
#1270
1-
1(
1$
#1275
0-
0(
0$
#1280
1-
1(
1$
#1285
0-
0(
0$
#1290
1-
1(
1$
#1295
0-
0(
0$
#1300
1-
1(
1$
#1305
0-
0(
0$
#1310
1-
1(
1$
#1315
0-
0(
0$
#1320
1-
1(
1$
#1325
0-
0(
0$
#1330
1-
1(
1$
#1335
0-
0(
0$
#1340
1-
1(
1$
