Ice40/PID/Modules/gtkwave/u(t) neg con reset/u(t)negWreset.v
// Code generated by Icestudio 0.3.3
// Sat, 01 Dec 2018 21:47:30 GMT

`default_nettype none

module main #(
 parameter vea947b = 5
) (
 input v1d1841,
 input v4d66c8,
 output vfa9c3f,
 output [0:4] vinit
);
 localparam p0 = vea947b;
 wire w1;
 wire w2;
 wire w3;
 assign vfa9c3f = w1;
 assign w2 = v1d1841;
 assign w3 = v4d66c8;
 v94027a #(
  .va1edee(p0)
 ) vc2b514 (
  .v19bd79(w1),
  .vdb65bd(w2),
  .ve9fb46(w3)
 );
 assign vinit = 5'b00000;
endmodule

module v94027a #(
 parameter va1edee = 0
) (
 input vdb65bd,
 input ve9fb46,
 output v19bd79
);
 localparam p1 = va1edee;
 wire w0;
 wire w2;
 wire w3;
 assign v19bd79 = w0;
 assign w2 = ve9fb46;
 assign w3 = vdb65bd;
 v94027a_v8c8712 #(
  .t(p1)
 ) v8c8712 (
  .u(w0),
  .clk(w2),
  .reset(w3)
 );
endmodule

module v94027a_v8c8712 #(
 parameter t = 0
) (
 input reset,
 input clk,
 output u
);
 // falling pulse in t
 // t ciclos de reloj a 1 y
 // cambia a 0.
 
 localparam num_periods=t;
 
 reg[7:0] contador=0;
 reg u=1'b1;
 
 
 always @(posedge clk)
 if(reset) contador<=0;
 else if(contador >= num_periods-1)
  begin
  u <=1'b0;
  contador <= contador;
  end
 else
  begin
   u<=1'b1;
   contador=contador+1;
  end
  
  
  
  
endmodule

Ice40/PID/Modules/gtkwave/u(t) neg con reset/u(t)negWreset_tb.v
// Code generated by Icestudio 0.3.3
// Sat, 01 Dec 2018 21:47:39 GMT

// Testbench template

`default_nettype none
`define DUMPSTR(x) `"x.vcd`"
`timescale 10 ns / 1 ns


module main_tb
;
 
 // Simulation time: 100ns (10 * 10ns)
 parameter DURATION = 110;                                      //**añado  duración de 110 (55 periodos)
 
 // TODO: edit the module parameters here
 // e.g. localparam constant_value = 1;
 localparam constant_Fall_In = 5;
 
 // Input/Output
 reg reset;
 reg reloj;
 wire u_neg;
 
 // Module instance
 main #(
  .vea947b(constant_Fall_In)
 ) MAIN (
  .v1d1841(reset),
  .v4d66c8(reloj),
  .vfa9c3f(u_neg)
 );
 
 always #1 reloj=~reloj;                                      //reloj del sistema
 
 initial begin
  // File were to store the simulation results
  $dumpfile(`DUMPSTR(`VCD_OUTPUT));
  $dumpvars(0, main_tb);
 
  // TODO: initialize the registers here
  // e.g. value = 1;
  // e.g. #2 value = 0;
  reset = 0;
  reloj = 1;
  #20 reset=1;
  #2  reset=0;
  #19 reset=1;
  #2  reset=0;
  #21 reset=1;
  #2  reset=0;
 
  #(DURATION) $display("End of simulation");
  $finish;
 end
 
endmodule

Ice40/PID/Modules/gtkwave/u(t) neg con reset/u(t)negWreset_tb.vcd
$date
	Sat Dec 01 22:52:15 2018
$end
$version
	Icarus Verilog
$end
$timescale
	1ns
$end
$scope module main_tb $end
$var wire 1 ! u_neg $end
$var reg 1 " reloj $end
$var reg 1 # reset $end
$scope module MAIN $end
$var wire 1 # v1d1841 $end
$var wire 1 " v4d66c8 $end
$var wire 1 ! vfa9c3f $end
$var wire 5 $ vinit [0:4] $end
$var wire 1 % w2 $end
$var wire 1 & w3 $end
$var wire 1 ' w1 $end
$scope module vc2b514 $end
$var wire 1 ' v19bd79 $end
$var wire 1 % vdb65bd $end
$var wire 1 & ve9fb46 $end
$var wire 1 ( w2 $end
$var wire 1 ) w3 $end
$var wire 1 * w0 $end
$scope module v8c8712 $end
$var wire 1 ( clk $end
$var wire 1 ) reset $end
$var reg 8 + contador [7:0] $end
$var reg 1 * u $end
$upscope $end
$upscope $end
$upscope $end
$upscope $end
$enddefinitions $end
#0
$dumpvars
b1 +
1*
0)
1(
1'
1&
0%
b0 $
0#
1"
1!
$end
#10
0(
0&
0"
#20
b10 +
1(
1&
1"
#30
0(
0&
0"
#40
b11 +
1(
1&
1"
#50
0(
0&
0"
#60
b100 +
1(
1&
1"
#70
0(
0&
0"
#80
0!
0'
0*
1(
1&
1"
#90
0(
0&
0"
#100
1(
1&
1"
#110
0(
0&
0"
#120
1(
1&
1"
#130
0(
0&
0"
#140
1(
1&
1"
#150
0(
0&
0"
#160
1(
1&
1"
#170
0(
0&
0"
#180
1(
1&
1"
#190
0(
0&
0"
#200
b0 +
1(
1&
1"
1)
1%
1#
#210
0(
0&
0"
#220
1!
1'
1*
b1 +
1(
1&
1"
0)
0%
0#
#230
0(
0&
0"
#240
b10 +
1(
1&
1"
#250
0(
0&
0"
#260
b11 +
1(
1&
1"
#270
0(
0&
0"
#280
b100 +
1(
1&
1"
#290
0(
0&
0"
#300
0!
0'
0*
1(
1&
1"
#310
0(
0&
0"
#320
1(
1&
1"
#330
0(
0&
0"
#340
1(
1&
1"
#350
0(
0&
0"
#360
1(
1&
1"
#370
0(
0&
0"
#380
1(
1&
1"
#390
0(
0&
0"
#400
1(
1&
1"
#410
0(
0&
0"
1)
1%
1#
#420
b0 +
1(
1&
1"
#430
0(
0&
0"
0)
0%
0#
#440
1!
1'
1*
b1 +
1(
1&
1"
#450
0(
0&
0"
#460
b10 +
1(
1&
1"
#470
0(
0&
0"
#480
b11 +
1(
1&
1"
#490
0(
0&
0"
#500
b100 +
1(
1&
1"
#510
0(
0&
0"
#520
0!
0'
0*
1(
1&
1"
#530
0(
0&
0"
#540
1(
1&
1"
#550
0(
0&
0"
#560
1(
1&
1"
#570
0(
0&
0"
#580
1(
1&
1"
#590
0(
0&
0"
#600
1(
1&
1"
#610
0(
0&
0"
#620
1(
1&
1"
#630
0(
0&
0"
#640
b0 +
1(
1&
1"
1)
1%
1#
#650
0(
0&
0"
#660
1!
1'
1*
b1 +
1(
1&
1"
0)
0%
0#
#670
0(
0&
0"
#680
b10 +
1(
1&
1"
#690
0(
0&
0"
#700
b11 +
1(
1&
1"
#710
0(
0&
0"
#720
b100 +
1(
1&
1"
#730
0(
0&
0"
#740
0!
0'
0*
1(
1&
1"
#750
0(
0&
0"
#760
1(
1&
1"
#770
0(
0&
0"
#780
1(
1&
1"
#790
0(
0&
0"
#800
1(
1&
1"
#810
0(
0&
0"
#820
1(
1&
1"
#830
0(
0&
0"
#840
1(
1&
1"
#850
0(
0&
0"
#860
1(
1&
1"
#870
0(
0&
0"
#880
1(
1&
1"
#890
0(
0&
0"
#900
1(
1&
1"
#910
0(
0&
0"
#920
1(
1&
1"
#930
0(
0&
0"
#940
1(
1&
1"
#950
0(
0&
0"
#960
1(
1&
1"
#970
0(
0&
0"
#980
1(
1&
1"
#990
0(
0&
0"
#1000
1(
1&
1"
#1010
0(
0&
0"
#1020
1(
1&
1"
#1030
0(
0&
0"
#1040
1(
1&
1"
#1050
0(
0&
0"
#1060
1(
1&
1"
#1070
0(
0&
0"
#1080
1(
1&
1"
#1090
0(
0&
0"
#1100
1(
1&
1"
#1110
0(
0&
0"
#1120
1(
1&
1"
#1130
0(
0&
0"
#1140
1(
1&
1"
#1150
0(
0&
0"
#1160
1(
1&
1"
#1170
0(
0&
0"
#1180
1(
1&
1"
#1190
0(
0&
0"
#1200
1(
1&
1"
#1210
0(
0&
0"
#1220
1(
1&
1"
#1230
0(
0&
0"
#1240
1(
1&
1"
#1250
0(
0&
0"
#1260
1(
1&
1"
#1270
0(
0&
0"
#1280
1(
1&
1"
#1290
0(
0&
0"
#1300
1(
1&
1"
#1310
0(
0&
0"
#1320
1(
1&
1"
#1330
0(
0&
0"
#1340
1(
1&
1"
#1350
0(
0&
0"
#1360
1(
1&
1"
#1370
0(
0&
0"
#1380
1(
1&
1"
#1390
0(
0&
0"
#1400
1(
1&
1"
#1410
0(
0&
0"
#1420
1(
1&
1"
#1430
0(
0&
0"
#1440
1(
1&
1"
#1450
0(
0&
0"
#1460
1(
1&
1"
#1470
0(
0&
0"
#1480
1(
1&
1"
#1490
0(
0&
0"
#1500
1(
1&
1"
#1510
0(
0&
0"
#1520
1(
1&
1"
#1530
0(
0&
0"
#1540
1(
1&
1"
#1550
0(
0&
0"
#1560
1(
1&
1"
#1570
0(
0&
0"
#1580
1(
1&
1"
#1590
0(
0&
0"
#1600
1(
1&
1"
#1610
0(
0&
0"
#1620
1(
1&
1"
#1630
0(
0&
0"
#1640
1(
1&
1"
#1650
0(
0&
0"
#1660
1(
1&
1"
#1670
0(
0&
0"
#1680
1(
1&
1"
#1690
0(
0&
0"
#1700
1(
1&
1"
#1710
0(
0&
0"
#1720
1(
1&
1"
#1730
0(
0&
0"
#1740
1(
1&
1"
#1750
0(
0&
0"
#1760
1(
1&
1"
