Ice40/Curso Verilog/gtkwave/combinacional/circuito1.v
// Code generated by Icestudio 0.3.3
// Thu, 15 Nov 2018 23:00:52 GMT

`default_nettype none

module main (
 input vfad476,
 input v6d9635,
 input vc75b73,
 input v343bc5,
 output vdbf484,
 output [0:7] vinit
);
 wire w0;
 wire w1;
 wire w2;
 wire w3;
 wire w4;
 wire w5;
 wire w6;
 assign vdbf484 = w2;
 assign w3 = vfad476;
 assign w4 = v6d9635;
 assign w5 = vc75b73;
 assign w6 = v343bc5;
 v816138 v97f5fb (
  .vcbab45(w0),
  .v0e28cb(w3),
  .v3ca442(w4)
 );
 v816138 v0d0f35 (
  .vcbab45(w1),
  .v0e28cb(w5),
  .v3ca442(w6)
 );
 vb2090f v7a2694 (
  .v0e28cb(w0),
  .v3ca442(w1),
  .vcbab45(w2)
 );
 assign vinit = 8'b00000000;
endmodule

module v816138 (
 input v0e28cb,
 input v3ca442,
 output vcbab45
);
 wire w0;
 wire w1;
 wire w2;
 assign w0 = v0e28cb;
 assign w1 = v3ca442;
 assign vcbab45 = w2;
 v816138_vf4938a vf4938a (
  .a(w0),
  .b(w1),
  .c(w2)
 );
endmodule

module v816138_vf4938a (
 input a,
 input b,
 output c
);
 //-- Puerta OR
 
 //-- module and (input wire a, input wire b,
 //--             output wire c);
 
 assign c = a | b;
 
 //-- endmodule
endmodule

module vb2090f (
 input v0e28cb,
 input v3ca442,
 output vcbab45
);
 wire w0;
 wire w1;
 wire w2;
 assign w0 = v0e28cb;
 assign w1 = v3ca442;
 assign vcbab45 = w2;
 vb2090f_vf4938a vf4938a (
  .a(w0),
  .b(w1),
  .c(w2)
 );
endmodule

module vb2090f_vf4938a (
 input a,
 input b,
 output c
);
 //-- Puerta AND
 
 //-- module and (input wire a, input wire b,
 //--             output wire c);
 
 assign c = a & b;
 
 //-- endmodule
endmodule

Ice40/Curso Verilog/gtkwave/combinacional/circuito1_tb.v
// Code generated by Icestudio 0.3.3
// Thu, 15 Nov 2018 23:01:08 GMT

// Testbench template

`default_nettype none
`define DUMPSTR(x) `"x.vcd`"
`timescale 10 ns / 1 ns


module main_tb
;
 
 // Simulation time: 100ns (10 * 10ns)
 parameter DURATION = 500;
 
 // Input/Output
 reg a;
 reg b;
 reg c;
 reg d;
 wire out;
 
 // Module instance
 main MAIN (
  .vfad476(a),
  .v6d9635(b),
  .vc75b73(c),
  .v343bc5(d),
  .vdbf484(out)
 );
 
 initial begin
  // File were to store the simulation results
  $dumpfile(`DUMPSTR(`VCD_OUTPUT));
  $dumpvars(0, main_tb);
 
  // TODO: initialize the registers here
  // e.g. value = 1;
  // e.g. #2 value = 0;
  a = 0;  b = 0;  c = 0;  d = 0;
  #2 a=0; b=0; c=0; d=1;
  #2 a=0; b=0; c=0; d=1;
  #2 a=0; b=0; c=1; d=0;
  #2 a=0; b=0; c=1; d=1;
  #2 a=0; b=1; c=0; d=0;
  #2 a=0; b=1; c=0; d=1;
  #2 a=0; b=1; c=1; d=0;
  #2 a=0; b=1; c=1; d=1;
  #2 a=1; b=0; c=0; d=0;
  #2 a=1; b=0; c=0; d=1;
  #2 a=1; b=0; c=1; d=0;
  #2 a=1; b=0; c=1; d=1;
  #2 a=1; b=1; c=0; d=0;
  #2 a=1; b=1; c=0; d=1;
  #2 a=1; b=1; c=1; d=0;
  #2 a=1; b=1; c=1; d=1;
  
 
  #(DURATION) $display("End of simulation");
  $finish;
 end
 
endmodule

Ice40/Curso Verilog/gtkwave/combinacional/circuito1_tb.vcd
$date
	Fri Nov 16 00:08:44 2018
$end
$version
	Icarus Verilog
$end
$timescale
	1ns
$end
$scope module main_tb $end
$var wire 1 ! out $end
$var reg 1 " a $end
$var reg 1 # b $end
$var reg 1 $ c $end
$var reg 1 % d $end
$scope module MAIN $end
$var wire 1 % v343bc5 $end
$var wire 1 # v6d9635 $end
$var wire 1 $ vc75b73 $end
$var wire 1 ! vdbf484 $end
$var wire 1 " vfad476 $end
$var wire 8 & vinit [0:7] $end
$var wire 1 ' w3 $end
$var wire 1 ( w4 $end
$var wire 1 ) w5 $end
$var wire 1 * w6 $end
$var wire 1 + w2 $end
$var wire 1 , w1 $end
$var wire 1 - w0 $end
$scope module v0d0f35 $end
$var wire 1 ) v0e28cb $end
$var wire 1 * v3ca442 $end
$var wire 1 , vcbab45 $end
$var wire 1 . w0 $end
$var wire 1 / w1 $end
$var wire 1 0 w2 $end
$scope module vf4938a $end
$var wire 1 . a $end
$var wire 1 / b $end
$var wire 1 0 c $end
$upscope $end
$upscope $end
$scope module v7a2694 $end
$var wire 1 , v3ca442 $end
$var wire 1 + vcbab45 $end
$var wire 1 1 w0 $end
$var wire 1 2 w1 $end
$var wire 1 3 w2 $end
$var wire 1 - v0e28cb $end
$scope module vf4938a $end
$var wire 1 1 a $end
$var wire 1 2 b $end
$var wire 1 3 c $end
$upscope $end
$upscope $end
$scope module v97f5fb $end
$var wire 1 ' v0e28cb $end
$var wire 1 ( v3ca442 $end
$var wire 1 - vcbab45 $end
$var wire 1 4 w0 $end
$var wire 1 5 w1 $end
$var wire 1 6 w2 $end
$scope module vf4938a $end
$var wire 1 4 a $end
$var wire 1 5 b $end
$var wire 1 6 c $end
$upscope $end
$upscope $end
$upscope $end
$upscope $end
$enddefinitions $end
#0
$dumpvars
06
05
04
03
02
01
00
0/
0.
0-
0,
0+
0*
0)
0(
0'
b0 &
0%
0$
0#
0"
0!
$end
#20
12
1,
10
1/
1*
1%
#60
0/
0*
0%
1.
1)
1$
#80
1/
1*
1%
#100
02
0,
00
11
1-
16
0/
0*
0%
0.
0)
0$
15
1(
1#
#120
1!
1+
13
12
1,
10
1/
1*
1%
#140
0/
0*
0%
1.
1)
1$
#160
1/
1*
1%
#180
0!
0+
03
02
0,
00
0/
0*
0%
0.
0)
0$
05
0(
0#
14
1'
1"
#200
1!
1+
13
12
1,
10
1/
1*
1%
#220
0/
0*
0%
1.
1)
1$
#240
1/
1*
1%
#260
0!
0+
03
02
0,
00
0/
0*
0%
0.
0)
0$
15
1(
1#
#280
1!
1+
13
12
1,
10
1/
1*
1%
#300
0/
0*
0%
1.
1)
1$
#320
1/
1*
1%
