Ice40/PID/Modules/gtkwave/pulseFromToWresetV1/pulseFromToWresetV1.v
// Code generated by Icestudio 0.3.3
// Sat, 01 Dec 2018 22:29:10 GMT

`default_nettype none

module main #(
 parameter v2365d7 = 4,
 parameter vb48f8b = 8
) (
 input va35852,
 input ve4392f,
 output v8c3b7b,
 output [0:4] vinit
);
 localparam p0 = v2365d7;
 localparam p1 = vb48f8b;
 wire w2;
 wire w3;
 wire w4;
 assign v8c3b7b = w2;
 assign w3 = va35852;
 assign w4 = ve4392f;
 v2e9a59 #(
  .v2b07d6(p0),
  .v4dd05a(p1)
 ) v34f03d (
  .vd67ea4(w2),
  .vf8ab06(w3),
  .v3f7fd6(w4)
 );
 assign vinit = 5'b00000;
endmodule

module v2e9a59 #(
 parameter v2b07d6 = 0,
 parameter v4dd05a = 0
) (
 input vf8ab06,
 input v3f7fd6,
 output vd67ea4
);
 localparam p1 = v2b07d6;
 localparam p4 = v4dd05a;
 wire w0;
 wire w2;
 wire w3;
 wire w5;
 wire w6;
 wire w7;
 wire w8;
 assign vd67ea4 = w0;
 assign w3 = v3f7fd6;
 assign w5 = v3f7fd6;
 assign w7 = vf8ab06;
 assign w8 = vf8ab06;
 assign w5 = w3;
 assign w8 = w7;
 v161240 vb8f207 (
  .vcbab45(w0),
  .v0e28cb(w2),
  .v3ca442(w6)
 );
 v92ac3f #(
  .va1edee(p4)
 ) v3b7f0a (
  .ve9fb46(w5),
  .v19bd79(w6),
  .vdb65bd(w8)
 );
 vba01cd #(
  .va1edee(p1)
 ) v716ff9 (
  .v19bd79(w2),
  .ve9fb46(w3),
  .v637c56(w7)
 );
endmodule

module v161240 (
 input v0e28cb,
 input v3ca442,
 output vcbab45
);
 wire w0;
 wire w1;
 wire w2;
 assign w0 = v0e28cb;
 assign w1 = v3ca442;
 assign vcbab45 = w2;
 v161240_vf4938a vf4938a (
  .a(w0),
  .b(w1),
  .c(w2)
 );
endmodule

module v161240_vf4938a (
 input a,
 input b,
 output c
);
 //-- Puerta AND
 
 assign c = a & b;
 
 
endmodule

module v92ac3f #(
 parameter va1edee = 0
) (
 input vdb65bd,
 input ve9fb46,
 output v19bd79
);
 localparam p1 = va1edee;
 wire w0;
 wire w2;
 wire w3;
 assign v19bd79 = w0;
 assign w2 = ve9fb46;
 assign w3 = vdb65bd;
 v92ac3f_v8c8712 #(
  .t(p1)
 ) v8c8712 (
  .u(w0),
  .clk(w2),
  .reset(w3)
 );
endmodule

module v92ac3f_v8c8712 #(
 parameter t = 0
) (
 input reset,
 input clk,
 output u
);
 // falling pulse in t
 // t ciclos de reloj a 1 y
 // cambia a 0.
 
 localparam num_periods=t;
 
 reg[7:0] contador=0;
 reg u=1'b1;
 
 
 always @(posedge clk)
 if(reset) contador<=0;
 else if(contador >= num_periods)
  begin
  u <=1'b0;
  contador <= contador;
  end
 else
  begin
   u<=1'b1;
   contador=contador+1;
  end
  
  
  
  
endmodule

module vba01cd #(
 parameter va1edee = 0
) (
 input v637c56,
 input ve9fb46,
 output v19bd79
);
 localparam p1 = va1edee;
 wire w0;
 wire w2;
 wire w3;
 assign v19bd79 = w0;
 assign w2 = ve9fb46;
 assign w3 = v637c56;
 vba01cd_v8c8712 #(
  .t(p1)
 ) v8c8712 (
  .u(w0),
  .clk(w2),
  .reset(w3)
 );
endmodule

module vba01cd_v8c8712 #(
 parameter t = 0
) (
 input reset,
 input clk,
 output u
);
 // Escalón u(t)
 // t ciclos de reloj a 0 y
 // cambia a 1.
 
 localparam num_periods=t;
 
 reg[7:0] contador=0;
 reg u=1'b0;
 
 
 always @(posedge clk)
 if(reset) contador<=0;
 else if(contador >= num_periods)
  begin
  u <=1'b1;
  contador <= contador;
  end
 else
  begin
   u<=1'b0;
   contador=contador+1;
  end
  
  
  
  
endmodule

Ice40/PID/Modules/gtkwave/pulseFromToWresetV1/pulseFromToWresetV1_tb.v
// Code generated by Icestudio 0.3.3
// Sat, 01 Dec 2018 22:29:52 GMT

// Testbench template

`default_nettype none
`define DUMPSTR(x) `"x.vcd`"
`timescale 10 ns / 1 ns


module main_tb
;
 
 // Simulation time: 100ns (10 * 10ns)
 parameter DURATION = 110;
 
 // TODO: edit the module parameters here
 // e.g. localparam constant_value = 1;
 localparam constant_Inicio = 4;
 localparam constant_Fin = 8;
 
 // Input/Output
 reg reset;
 reg reloj;
 wire pulso;
 
 // Module instance
 main #(
  .v2365d7(constant_Inicio),
  .vb48f8b(constant_Fin)
 ) MAIN (
  .va35852(reset),
  .ve4392f(reloj),
  .v8c3b7b(pulso)
 );
 
 always #1 reloj=~reloj;
 
 initial begin
  // File were to store the simulation results
  $dumpfile(`DUMPSTR(`VCD_OUTPUT));
  $dumpvars(0, main_tb);
 
  // TODO: initialize the registers here
  // e.g. value = 1;
  // e.g. #2 value = 0;
  reset = 0;
  reloj = 1;
  #20 reset=1;
  #2  reset=0;
  #19 reset=1;
  #2  reset=0;
  #21 reset=1;
  #2  reset=0;
  
 
  #(DURATION) $display("End of simulation");
  $finish;
 end
 
endmodule

Ice40/PID/Modules/gtkwave/pulseFromToWresetV1/pulseFromToWresetV1_tb.vcd
$date
	Sat Dec 01 23:58:52 2018
$end
$version
	Icarus Verilog
$end
$timescale
	1ns
$end
$scope module main_tb $end
$var wire 1 ! pulso $end
$var reg 1 " reloj $end
$var reg 1 # reset $end
$scope module MAIN $end
$var wire 1 ! v8c3b7b $end
$var wire 1 # va35852 $end
$var wire 1 " ve4392f $end
$var wire 5 $ vinit [0:4] $end
$var wire 1 % w3 $end
$var wire 1 & w4 $end
$var wire 1 ' w2 $end
$scope module v34f03d $end
$var wire 1 & v3f7fd6 $end
$var wire 1 ' vd67ea4 $end
$var wire 1 % vf8ab06 $end
$var wire 1 ( w3 $end
$var wire 1 ) w5 $end
$var wire 1 * w7 $end
$var wire 1 + w8 $end
$var wire 1 , w6 $end
$var wire 1 - w2 $end
$var wire 1 . w0 $end
$scope module v3b7f0a $end
$var wire 1 , v19bd79 $end
$var wire 1 + vdb65bd $end
$var wire 1 ) ve9fb46 $end
$var wire 1 / w2 $end
$var wire 1 0 w3 $end
$var wire 1 1 w0 $end
$scope module v8c8712 $end
$var wire 1 / clk $end
$var wire 1 0 reset $end
$var reg 8 2 contador [7:0] $end
$var reg 1 1 u $end
$upscope $end
$upscope $end
$scope module v716ff9 $end
$var wire 1 - v19bd79 $end
$var wire 1 * v637c56 $end
$var wire 1 ( ve9fb46 $end
$var wire 1 3 w2 $end
$var wire 1 4 w3 $end
$var wire 1 5 w0 $end
$scope module v8c8712 $end
$var wire 1 3 clk $end
$var wire 1 4 reset $end
$var reg 8 6 contador [7:0] $end
$var reg 1 5 u $end
$upscope $end
$upscope $end
$scope module vb8f207 $end
$var wire 1 - v0e28cb $end
$var wire 1 , v3ca442 $end
$var wire 1 . vcbab45 $end
$var wire 1 7 w0 $end
$var wire 1 8 w1 $end
$var wire 1 9 w2 $end
$scope module vf4938a $end
$var wire 1 7 a $end
$var wire 1 8 b $end
$var wire 1 9 c $end
$upscope $end
$upscope $end
$upscope $end
$upscope $end
$upscope $end
$enddefinitions $end
#0
$dumpvars
09
18
07
b1 6
05
04
13
b1 2
11
00
1/
0.
0-
1,
0+
0*
1)
1(
0'
1&
0%
b0 $
0#
1"
0!
$end
#10
03
0(
0/
0)
0&
0"
#20
b10 6
b10 2
13
1(
1/
1)
1&
1"
#30
03
0(
0/
0)
0&
0"
#40
b11 6
b11 2
13
1(
1/
1)
1&
1"
#50
03
0(
0/
0)
0&
0"
#60
b100 6
b100 2
13
1(
1/
1)
1&
1"
#70
03
0(
0/
0)
0&
0"
#80
1!
1'
1.
19
17
1-
15
b101 2
13
1(
1/
1)
1&
1"
#90
03
0(
0/
0)
0&
0"
#100
b110 2
13
1(
1/
1)
1&
1"
#110
03
0(
0/
0)
0&
0"
#120
b111 2
13
1(
1/
1)
1&
1"
#130
03
0(
0/
0)
0&
0"
#140
b1000 2
13
1(
1/
1)
1&
1"
#150
03
0(
0/
0)
0&
0"
#160
0!
0'
0.
09
08
0,
01
13
1(
1/
1)
1&
1"
#170
03
0(
0/
0)
0&
0"
#180
13
1(
1/
1)
1&
1"
#190
03
0(
0/
0)
0&
0"
#200
b0 6
b0 2
13
1(
1/
1)
1&
1"
14
1*
10
1+
1%
1#
#210
03
0(
0/
0)
0&
0"
#220
07
0-
05
18
1,
11
b1 6
b1 2
13
1(
1/
1)
1&
1"
04
0*
00
0+
0%
0#
#230
03
0(
0/
0)
0&
0"
#240
b10 6
b10 2
13
1(
1/
1)
1&
1"
#250
03
0(
0/
0)
0&
0"
#260
b11 6
b11 2
13
1(
1/
1)
1&
1"
#270
03
0(
0/
0)
0&
0"
#280
b100 6
b100 2
13
1(
1/
1)
1&
1"
#290
03
0(
0/
0)
0&
0"
#300
1!
1'
1.
19
17
1-
15
b101 2
13
1(
1/
1)
1&
1"
#310
03
0(
0/
0)
0&
0"
#320
b110 2
13
1(
1/
1)
1&
1"
#330
03
0(
0/
0)
0&
0"
#340
b111 2
13
1(
1/
1)
1&
1"
#350
03
0(
0/
0)
0&
0"
#360
b1000 2
13
1(
1/
1)
1&
1"
#370
03
0(
0/
0)
0&
0"
#380
0!
0'
0.
09
08
0,
01
13
1(
1/
1)
1&
1"
#390
03
0(
0/
0)
0&
0"
#400
13
1(
1/
1)
1&
1"
#410
03
0(
0/
0)
0&
0"
14
1*
10
1+
1%
1#
#420
b0 6
b0 2
13
1(
1/
1)
1&
1"
#430
03
0(
0/
0)
0&
0"
04
0*
00
0+
0%
0#
#440
07
0-
05
18
1,
11
b1 6
b1 2
13
1(
1/
1)
1&
1"
#450
03
0(
0/
0)
0&
0"
#460
b10 6
b10 2
13
1(
1/
1)
1&
1"
#470
03
0(
0/
0)
0&
0"
#480
b11 6
b11 2
13
1(
1/
1)
1&
1"
#490
03
0(
0/
0)
0&
0"
#500
b100 6
b100 2
13
1(
1/
1)
1&
1"
#510
03
0(
0/
0)
0&
0"
#520
1!
1'
1.
19
17
1-
15
b101 2
13
1(
1/
1)
1&
1"
#530
03
0(
0/
0)
0&
0"
#540
b110 2
13
1(
1/
1)
1&
1"
#550
03
0(
0/
0)
0&
0"
#560
b111 2
13
1(
1/
1)
1&
1"
#570
03
0(
0/
0)
0&
0"
#580
b1000 2
13
1(
1/
1)
1&
1"
#590
03
0(
0/
0)
0&
0"
#600
0!
0'
0.
09
08
0,
01
13
1(
1/
1)
1&
1"
#610
03
0(
0/
0)
0&
0"
#620
13
1(
1/
1)
1&
1"
#630
03
0(
0/
0)
0&
0"
#640
b0 6
b0 2
13
1(
1/
1)
1&
1"
14
1*
10
1+
1%
1#
#650
03
0(
0/
0)
0&
0"
#660
07
0-
05
18
1,
11
b1 6
b1 2
13
1(
1/
1)
1&
1"
04
0*
00
0+
0%
0#
#670
03
0(
0/
0)
0&
0"
#680
b10 6
b10 2
13
1(
1/
1)
1&
1"
#690
03
0(
0/
0)
0&
0"
#700
b11 6
b11 2
13
1(
1/
1)
1&
1"
#710
03
0(
0/
0)
0&
0"
#720
b100 6
b100 2
13
1(
1/
1)
1&
1"
#730
03
0(
0/
0)
0&
0"
#740
1!
1'
1.
19
17
1-
15
b101 2
13
1(
1/
1)
1&
1"
#750
03
0(
0/
0)
0&
0"
#760
b110 2
13
1(
1/
1)
1&
1"
#770
03
0(
0/
0)
0&
0"
#780
b111 2
13
1(
1/
1)
1&
1"
#790
03
0(
0/
0)
0&
0"
#800
b1000 2
13
1(
1/
1)
1&
1"
#810
03
0(
0/
0)
0&
0"
#820
0!
0'
0.
09
08
0,
01
13
1(
1/
1)
1&
1"
#830
03
0(
0/
0)
0&
0"
#840
13
1(
1/
1)
1&
1"
#850
03
0(
0/
0)
0&
0"
#860
13
1(
1/
1)
1&
1"
#870
03
0(
0/
0)
0&
0"
#880
13
1(
1/
1)
1&
1"
#890
03
0(
0/
0)
0&
0"
#900
13
1(
1/
1)
1&
1"
#910
03
0(
0/
0)
0&
0"
#920
13
1(
1/
1)
1&
1"
#930
03
0(
0/
0)
0&
0"
#940
13
1(
1/
1)
1&
1"
#950
03
0(
0/
0)
0&
0"
#960
13
1(
1/
1)
1&
1"
#970
03
0(
0/
0)
0&
0"
#980
13
1(
1/
1)
1&
1"
#990
03
0(
0/
0)
0&
0"
#1000
13
1(
1/
1)
1&
1"
#1010
03
0(
0/
0)
0&
0"
#1020
13
1(
1/
1)
1&
1"
#1030
03
0(
0/
0)
0&
0"
#1040
13
1(
1/
1)
1&
1"
#1050
03
0(
0/
0)
0&
0"
#1060
13
1(
1/
1)
1&
1"
#1070
03
0(
0/
0)
0&
0"
#1080
13
1(
1/
1)
1&
1"
#1090
03
0(
0/
0)
0&
0"
#1100
13
1(
1/
1)
1&
1"
#1110
03
0(
0/
0)
0&
0"
#1120
13
1(
1/
1)
1&
1"
#1130
03
0(
0/
0)
0&
0"
#1140
13
1(
1/
1)
1&
1"
#1150
03
0(
0/
0)
0&
0"
#1160
13
1(
1/
1)
1&
1"
#1170
03
0(
0/
0)
0&
0"
#1180
13
1(
1/
1)
1&
1"
#1190
03
0(
0/
0)
0&
0"
#1200
13
1(
1/
1)
1&
1"
#1210
03
0(
0/
0)
0&
0"
#1220
13
1(
1/
1)
1&
1"
#1230
03
0(
0/
0)
0&
0"
#1240
13
1(
1/
1)
1&
1"
#1250
03
0(
0/
0)
0&
0"
#1260
13
1(
1/
1)
1&
1"
#1270
03
0(
0/
0)
0&
0"
#1280
13
1(
1/
1)
1&
1"
#1290
03
0(
0/
0)
0&
0"
#1300
13
1(
1/
1)
1&
1"
#1310
03
0(
0/
0)
0&
0"
#1320
13
1(
1/
1)
1&
1"
#1330
03
0(
0/
0)
0&
0"
#1340
13
1(
1/
1)
1&
1"
#1350
03
0(
0/
0)
0&
0"
#1360
13
1(
1/
1)
1&
1"
#1370
03
0(
0/
0)
0&
0"
#1380
13
1(
1/
1)
1&
1"
#1390
03
0(
0/
0)
0&
0"
#1400
13
1(
1/
1)
1&
1"
#1410
03
0(
0/
0)
0&
0"
#1420
13
1(
1/
1)
1&
1"
#1430
03
0(
0/
0)
0&
0"
#1440
13
1(
1/
1)
1&
1"
#1450
03
0(
0/
0)
0&
0"
#1460
13
1(
1/
1)
1&
1"
#1470
03
0(
0/
0)
0&
0"
#1480
13
1(
1/
1)
1&
1"
#1490
03
0(
0/
0)
0&
0"
#1500
13
1(
1/
1)
1&
1"
#1510
03
0(
0/
0)
0&
0"
#1520
13
1(
1/
1)
1&
1"
#1530
03
0(
0/
0)
0&
0"
#1540
13
1(
1/
1)
1&
1"
#1550
03
0(
0/
0)
0&
0"
#1560
13
1(
1/
1)
1&
1"
#1570
03
0(
0/
0)
0&
0"
#1580
13
1(
1/
1)
1&
1"
#1590
03
0(
0/
0)
0&
0"
#1600
13
1(
1/
1)
1&
1"
#1610
03
0(
0/
0)
0&
0"
#1620
13
1(
1/
1)
1&
1"
#1630
03
0(
0/
0)
0&
0"
#1640
13
1(
1/
1)
1&
1"
#1650
03
0(
0/
0)
0&
0"
#1660
13
1(
1/
1)
1&
1"
#1670
03
0(
0/
0)
0&
0"
#1680
13
1(
1/
1)
1&
1"
#1690
03
0(
0/
0)
0&
0"
#1700
13
1(
1/
1)
1&
1"
#1710
03
0(
0/
0)
0&
0"
#1720
13
1(
1/
1)
1&
1"
#1730
03
0(
0/
0)
0&
0"
#1740
13
1(
1/
1)
1&
1"
#1750
03
0(
0/
0)
0&
0"
#1760
13
1(
1/
1)
1&
1"
