Ice40/Modulos/Pulso/PulseIn/gtkwave/PulseInV2/PulseInV2_test.v
// Code generated by Icestudio 0.3.3
// Mon, 03 Dec 2018 00:31:49 GMT

`default_nettype none

module main (
 input vd748c5,
 input v80c520,
 input vc31cf8,
 output [15:0] v0755f8,
 output [15:0] vfb470d,
 output v25a280,
 output [0:4] vinit
);
 wire [0:15] w0;
 wire [0:15] w1;
 wire w2;
 wire w3;
 wire w4;
 wire w5;
 wire w6;
 wire w7;
 wire w8;
 wire w9;
 wire w10;
 wire w11;
 wire w12;
 wire w13;
 wire [0:15] w14;
 assign vfb470d = w1;
 assign w2 = vd748c5;
 assign w4 = vd748c5;
 assign v25a280 = w5;
 assign w6 = vd748c5;
 assign w7 = v80c520;
 assign w9 = v80c520;
 assign w11 = v80c520;
 assign w12 = vc31cf8;
 assign w13 = vc31cf8;
 assign v0755f8 = w14;
 assign w4 = w2;
 assign w5 = w3;
 assign w6 = w2;
 assign w6 = w4;
 assign w9 = w7;
 assign w10 = w3;
 assign w10 = w5;
 assign w11 = w7;
 assign w11 = w9;
 assign w13 = w12;
 assign w14 = w0;
 v528969 v97e3b5 (
  .vcbab45(w8),
  .v0e28cb(w9),
  .v3ca442(w10)
 );
 v8243c9 v4e5ed4 (
  .v26b754(w0),
  .vdd729a(w6),
  .ve61673(w8),
  .v7c533e(w13)
 );
 vcda464 v2184ee (
  .v11536b(w0),
  .v01aa16(w1),
  .v97b64a(w2),
  .vc3ff44(w3),
  .v9d2436(w11)
 );
 v69d0bb vd54a50 (
  .v317e8f(w3),
  .v02d455(w4),
  .v4ae82c(w7),
  .v08bfd6(w12)
 );
 assign vinit = 5'b00000;
endmodule

module v528969 (
 input v0e28cb,
 input v3ca442,
 output vcbab45
);
 wire w0;
 wire w1;
 wire w2;
 assign w0 = v0e28cb;
 assign w1 = v3ca442;
 assign vcbab45 = w2;
 v528969_vf4938a vf4938a (
  .a(w0),
  .b(w1),
  .c(w2)
 );
endmodule

module v528969_vf4938a (
 input a,
 input b,
 output c
);
 // OR logic gate
 
 assign c = a | b;
endmodule

module v8243c9 (
 input vdd729a,
 input ve61673,
 input v7c533e,
 output [15:0] v26b754
);
 wire w0;
 wire w1;
 wire w2;
 wire [0:15] w3;
 assign w0 = ve61673;
 assign w1 = vdd729a;
 assign w2 = v7c533e;
 assign v26b754 = w3;
 v8243c9_vbd6086 vbd6086 (
  .rst(w0),
  .clk(w1),
  .en(w2),
  .q(w3)
 );
endmodule

module v8243c9_vbd6086 (
 input clk,
 input rst,
 input en,
 output [15:0] q
);
 //-- Numero de bits del contador
 localparam N = 16;      // 16 bits
 localparam M = 2**N-1;  // 2^16 -1 = 65535
                         // cuenta de 0 a 65535
 reg [N-1:0] qi = 0;
 
 always @(posedge clk)
   if (rst)
     qi <= 0;
   else if (en)
       qi <= qi + 1; //Suma cuando esté 
                     //habilitado
   else qi<=qi;
   
 assign q = qi;
 
 
     
endmodule

module vcda464 (
 input [15:0] v11536b,
 input vc3ff44,
 input v9d2436,
 input v97b64a,
 output [15:0] v01aa16
);
 wire [0:15] w0;
 wire [0:15] w1;
 wire w2;
 wire w3;
 wire w4;
 assign v01aa16 = w0;
 assign w1 = v11536b;
 assign w2 = v9d2436;
 assign w3 = vc3ff44;
 assign w4 = v97b64a;
 vcda464_v67385c v67385c (
  .q(w0),
  .d(w1),
  .reset(w2),
  .load(w3),
  .clk(w4)
 );
endmodule

module vcda464_v67385c (
 input [15:0] d,
 input load,
 input reset,
 input clk,
 output [15:0] q
);
 
 reg[15:0] qi=0;
 
 always @(posedge clk or posedge reset)
 if(reset)
  qi<=0;
 else if(load)
   qi<=d;
 else
  qi<=qi;
  
 assign q=qi;
 
 
 
endmodule

module v69d0bb (
 input v02d455,
 input v4ae82c,
 input v08bfd6,
 output v317e8f
);
 wire w0;
 wire w1;
 wire w2;
 wire w3;
 assign v317e8f = w0;
 assign w1 = v4ae82c;
 assign w2 = v02d455;
 assign w3 = v08bfd6;
 v69d0bb_v3523b6 v3523b6 (
  .Falling(w0),
  .reset(w1),
  .clk(w2),
  .in(w3)
 );
endmodule

module v69d0bb_v3523b6 (
 input clk,
 input reset,
 input in,
 output Falling
);
 
 reg Q1=0,Q2=0;
 
 //Biestable D donde capturo estado actual (in) y anterior (Q)
 always @(posedge clk)
 if(reset)
    begin
       Q1<=1'b0;
       Q2<=1'b0;
    end 
 else
    begin       //Dos biestables encadenados
      Q1<=in;
      Q2<=Q1;
    end 
 
 //Con datos del estado actual ya anterior, realizando un circutio combinacional
 //puedo saber si la señal ha cambiado y si ha subido o ha bajado el flanco.
 
 assign Falling = (~in & Q2)& ~reset ; // Si in (Actual) es 0 pero antes (Q) era 1 -->Falling
 
endmodule

Ice40/Modulos/Pulso/PulseIn/gtkwave/PulseInV2/PulseInV2_test_tb.v
// Code generated by Icestudio 0.3.3
// Mon, 03 Dec 2018 00:31:59 GMT

// Testbench template

`default_nettype none
`define DUMPSTR(x) `"x.vcd`"
`timescale 10 ns / 1 ns


module main_tb
;
 
 // Simulation time: 100ns (10 * 10ns)
 parameter DURATION = 100;
 
 // Input/Output
 reg clk;
 reg reset;
 reg InPulse;
 wire [15:0] count;
 wire [15:0] valor;
 wire Ready;
 
 // Module instance
 main MAIN (
  .vd748c5(clk),
  .v80c520(reset),
  .vc31cf8(InPulse),
  .v0755f8(count),
  .vfb470d(valor),
  .v25a280(Ready)
 );
 
 // Clock signal
 always #0.5 clk = ~clk;
 
 initial begin
  // File were to store the simulation results
  $dumpfile(`DUMPSTR(`VCD_OUTPUT));
  $dumpvars(0, main_tb);
 
  // TODO: initialize the registers here
  // e.g. value = 1;
  // e.g. #2 value = 0;
  clk = 1;
  reset = 0;
  InPulse = 0;
  #4 InPulse=1;
  #10 InPulse=0;
  #4   InPulse=1;
  #1   InPulse=0;
  #4   InPulse=1;
  #3   reset=1;
  #1   reset=0;
  #4   InPulse=0;
  #5   InPulse=1;
  #3   InPulse=0;
  
 
  #(DURATION) $display("End of simulation");
  $finish;
 end
 
endmodule

Ice40/Modulos/Pulso/PulseIn/gtkwave/PulseInV2/PulseInV2_test_tb.vcd
$date
	Mon Dec 03 01:34:11 2018
$end
$version
	Icarus Verilog
$end
$timescale
	1ns
$end
$scope module main_tb $end
$var wire 16 ! valor [15:0] $end
$var wire 16 " count [15:0] $end
$var wire 1 # Ready $end
$var reg 1 $ InPulse $end
$var reg 1 % clk $end
$var reg 1 & reset $end
$scope module MAIN $end
$var wire 16 ' v0755f8 [15:0] $end
$var wire 1 # v25a280 $end
$var wire 1 & v80c520 $end
$var wire 1 $ vc31cf8 $end
$var wire 1 % vd748c5 $end
$var wire 16 ( vfb470d [15:0] $end
$var wire 5 ) vinit [0:4] $end
$var wire 1 * w10 $end
$var wire 1 + w11 $end
$var wire 1 , w12 $end
$var wire 1 - w13 $end
$var wire 16 . w14 [0:15] $end
$var wire 1 / w2 $end
$var wire 1 0 w4 $end
$var wire 1 1 w5 $end
$var wire 1 2 w6 $end
$var wire 1 3 w7 $end
$var wire 1 4 w9 $end
$var wire 1 5 w8 $end
$var wire 1 6 w3 $end
$var wire 16 7 w1 [0:15] $end
$var wire 16 8 w0 [0:15] $end
$scope module v2184ee $end
$var wire 16 9 v01aa16 [15:0] $end
$var wire 1 / v97b64a $end
$var wire 1 + v9d2436 $end
$var wire 16 : w1 [0:15] $end
$var wire 1 ; w2 $end
$var wire 1 < w3 $end
$var wire 1 = w4 $end
$var wire 16 > w0 [0:15] $end
$var wire 1 6 vc3ff44 $end
$var wire 16 ? v11536b [15:0] $end
$scope module v67385c $end
$var wire 1 = clk $end
$var wire 16 @ d [15:0] $end
$var wire 1 < load $end
$var wire 1 ; reset $end
$var wire 16 A q [15:0] $end
$var reg 16 B qi [15:0] $end
$upscope $end
$upscope $end
$scope module v4e5ed4 $end
$var wire 16 C v26b754 [15:0] $end
$var wire 1 - v7c533e $end
$var wire 1 2 vdd729a $end
$var wire 1 D w0 $end
$var wire 1 E w1 $end
$var wire 1 F w2 $end
$var wire 16 G w3 [0:15] $end
$var wire 1 5 ve61673 $end
$scope module vbd6086 $end
$var wire 1 E clk $end
$var wire 1 F en $end
$var wire 1 D rst $end
$var wire 16 H q [15:0] $end
$var reg 16 I qi [15:0] $end
$upscope $end
$upscope $end
$scope module v97e3b5 $end
$var wire 1 4 v0e28cb $end
$var wire 1 * v3ca442 $end
$var wire 1 5 vcbab45 $end
$var wire 1 J w0 $end
$var wire 1 K w1 $end
$var wire 1 L w2 $end
$scope module vf4938a $end
$var wire 1 J a $end
$var wire 1 K b $end
$var wire 1 L c $end
$upscope $end
$upscope $end
$scope module vd54a50 $end
$var wire 1 0 v02d455 $end
$var wire 1 , v08bfd6 $end
$var wire 1 6 v317e8f $end
$var wire 1 3 v4ae82c $end
$var wire 1 M w1 $end
$var wire 1 N w2 $end
$var wire 1 O w3 $end
$var wire 1 P w0 $end
$scope module v3523b6 $end
$var wire 1 P Falling $end
$var wire 1 N clk $end
$var wire 1 O in $end
$var wire 1 M reset $end
$var reg 1 Q Q1 $end
$var reg 1 R Q2 $end
$upscope $end
$upscope $end
$upscope $end
$upscope $end
$enddefinitions $end
#0
$dumpvars
0R
0Q
0P
0O
1N
0M
0L
0K
0J
b0 I
b0 H
b0 G
0F
1E
0D
b0 C
b0 B
b0 A
b0 @
b0 ?
b0 >
1=
0<
0;
b0 :
b0 9
b0 8
b0 7
06
05
04
03
12
01
10
1/
b0 .
0-
0,
0+
0*
b0 )
b0 (
b0 '
0&
1%
0$
0#
b0 "
b0 !
$end
#5
0=
0/
0N
00
0E
02
0%
#10
1=
1/
1N
10
1E
12
1%
#15
0=
0/
0N
00
0E
02
0%
#20
1=
1/
1N
10
1E
12
1%
#25
0=
0/
0N
00
0E
02
0%
#30
1=
1/
1N
10
1E
12
1%
#35
0=
0/
0N
00
0E
02
0%
#40
1Q
b1 :
b1 @
b1 "
b1 '
b1 .
b1 8
b1 ?
b1 C
b1 G
b1 H
b1 I
1=
1/
1N
10
1E
12
1%
1O
1,
1F
1-
1$
#45
0=
0/
0N
00
0E
02
0%
#50
1R
b10 :
b10 @
b10 "
b10 '
b10 .
b10 8
b10 ?
b10 C
b10 G
b10 H
b10 I
1=
1/
1N
10
1E
12
1%
#55
0=
0/
0N
00
0E
02
0%
#60
b11 :
b11 @
b11 "
b11 '
b11 .
b11 8
b11 ?
b11 C
b11 G
b11 H
b11 I
1=
1/
1N
10
1E
12
1%
#65
0=
0/
0N
00
0E
02
0%
#70
b100 :
b100 @
b100 "
b100 '
b100 .
b100 8
b100 ?
b100 C
b100 G
b100 H
b100 I
1=
1/
1N
10
1E
12
1%
#75
0=
0/
0N
00
0E
02
0%
#80
b101 :
b101 @
b101 "
b101 '
b101 .
b101 8
b101 ?
b101 C
b101 G
b101 H
b101 I
1=
1/
1N
10
1E
12
1%
#85
0=
0/
0N
00
0E
02
0%
#90
b110 :
b110 @
b110 "
b110 '
b110 .
b110 8
b110 ?
b110 C
b110 G
b110 H
b110 I
1=
1/
1N
10
1E
12
1%
#95
0=
0/
0N
00
0E
02
0%
#100
b111 :
b111 @
b111 "
b111 '
b111 .
b111 8
b111 ?
b111 C
b111 G
b111 H
b111 I
1=
1/
1N
10
1E
12
1%
#105
0=
0/
0N
00
0E
02
0%
#110
b1000 :
b1000 @
b1000 "
b1000 '
b1000 .
b1000 8
b1000 ?
b1000 C
b1000 G
b1000 H
b1000 I
1=
1/
1N
10
1E
12
1%
#115
0=
0/
0N
00
0E
02
0%
#120
b1001 :
b1001 @
b1001 "
b1001 '
b1001 .
b1001 8
b1001 ?
b1001 C
b1001 G
b1001 H
b1001 I
1=
1/
1N
10
1E
12
1%
#125
0=
0/
0N
00
0E
02
0%
#130
b1010 :
b1010 @
b1010 "
b1010 '
b1010 .
b1010 8
b1010 ?
b1010 C
b1010 G
b1010 H
b1010 I
1=
1/
1N
10
1E
12
1%
#135
0=
0/
0N
00
0E
02
0%
#140
0Q
1D
15
1L
1<
1K
1*
1#
11
16
1P
1=
1/
1N
10
1E
12
1%
0O
0,
0F
0-
0$
#145
0=
0/
0N
00
0E
02
0%
#150
0D
05
0L
0<
0K
0*
0#
01
06
0P
b1010 !
b1010 (
b1010 7
b1010 9
b1010 >
b1010 A
b1010 B
0R
b0 :
b0 @
b0 "
b0 '
b0 .
b0 8
b0 ?
b0 C
b0 G
b0 H
b0 I
1=
1/
1N
10
1E
12
1%
#155
0=
0/
0N
00
0E
02
0%
#160
1=
1/
1N
10
1E
12
1%
#165
0=
0/
0N
00
0E
02
0%
#170
1=
1/
1N
10
1E
12
1%
#175
0=
0/
0N
00
0E
02
0%
#180
1Q
b1 :
b1 @
b1 "
b1 '
b1 .
b1 8
b1 ?
b1 C
b1 G
b1 H
b1 I
1=
1/
1N
10
1E
12
1%
1O
1,
1F
1-
1$
#185
0=
0/
0N
00
0E
02
0%
#190
1D
15
1L
1<
1K
1*
1#
11
16
1P
1R
0Q
1=
1/
1N
10
1E
12
1%
0O
0,
0F
0-
0$
#195
0=
0/
0N
00
0E
02
0%
#200
0D
05
0L
0<
0K
0*
0#
01
06
0P
b1 !
b1 (
b1 7
b1 9
b1 >
b1 A
b1 B
0R
b0 :
b0 @
b0 "
b0 '
b0 .
b0 8
b0 ?
b0 C
b0 G
b0 H
b0 I
1=
1/
1N
10
1E
12
1%
#205
0=
0/
0N
00
0E
02
0%
#210
1=
1/
1N
10
1E
12
1%
#215
0=
0/
0N
00
0E
02
0%
#220
1=
1/
1N
10
1E
12
1%
#225
0=
0/
0N
00
0E
02
0%
#230
1Q
b1 :
b1 @
b1 "
b1 '
b1 .
b1 8
b1 ?
b1 C
b1 G
b1 H
b1 I
1=
1/
1N
10
1E
12
1%
1O
1,
1F
1-
1$
#235
0=
0/
0N
00
0E
02
0%
#240
1R
b10 :
b10 @
b10 "
b10 '
b10 .
b10 8
b10 ?
b10 C
b10 G
b10 H
b10 I
1=
1/
1N
10
1E
12
1%
#245
0=
0/
0N
00
0E
02
0%
#250
b11 :
b11 @
b11 "
b11 '
b11 .
b11 8
b11 ?
b11 C
b11 G
b11 H
b11 I
1=
1/
1N
10
1E
12
1%
#255
0=
0/
0N
00
0E
02
0%
#260
0R
0Q
b0 :
b0 @
b0 "
b0 '
b0 .
b0 8
b0 ?
b0 C
b0 G
b0 H
b0 I
b0 !
b0 (
b0 7
b0 9
b0 >
b0 A
b0 B
1D
15
1L
1=
1/
1N
10
1E
12
1%
1M
13
1J
14
1;
1+
1&
#265
0=
0/
0N
00
0E
02
0%
#270
1Q
b1 :
b1 @
b1 "
b1 '
b1 .
b1 8
b1 ?
b1 C
b1 G
b1 H
b1 I
0D
05
0L
1=
1/
1N
10
1E
12
1%
0M
03
0J
04
0;
0+
0&
#275
0=
0/
0N
00
0E
02
0%
#280
1R
b10 :
b10 @
b10 "
b10 '
b10 .
b10 8
b10 ?
b10 C
b10 G
b10 H
b10 I
1=
1/
1N
10
1E
12
1%
#285
0=
0/
0N
00
0E
02
0%
#290
b11 :
b11 @
b11 "
b11 '
b11 .
b11 8
b11 ?
b11 C
b11 G
b11 H
b11 I
1=
1/
1N
10
1E
12
1%
#295
0=
0/
0N
00
0E
02
0%
#300
b100 :
b100 @
b100 "
b100 '
b100 .
b100 8
b100 ?
b100 C
b100 G
b100 H
b100 I
1=
1/
1N
10
1E
12
1%
#305
0=
0/
0N
00
0E
02
0%
#310
0Q
1D
15
1L
1<
1K
1*
1#
11
16
1P
1=
1/
1N
10
1E
12
1%
0O
0,
0F
0-
0$
#315
0=
0/
0N
00
0E
02
0%
#320
0D
05
0L
0<
0K
0*
0#
01
06
0P
b100 !
b100 (
b100 7
b100 9
b100 >
b100 A
b100 B
0R
b0 :
b0 @
b0 "
b0 '
b0 .
b0 8
b0 ?
b0 C
b0 G
b0 H
b0 I
1=
1/
1N
10
1E
12
1%
#325
0=
0/
0N
00
0E
02
0%
#330
1=
1/
1N
10
1E
12
1%
#335
0=
0/
0N
00
0E
02
0%
#340
1=
1/
1N
10
1E
12
1%
#345
0=
0/
0N
00
0E
02
0%
#350
1=
1/
1N
10
1E
12
1%
#355
0=
0/
0N
00
0E
02
0%
#360
1Q
b1 :
b1 @
b1 "
b1 '
b1 .
b1 8
b1 ?
b1 C
b1 G
b1 H
b1 I
1=
1/
1N
10
1E
12
1%
1O
1,
1F
1-
1$
#365
0=
0/
0N
00
0E
02
0%
#370
1R
b10 :
b10 @
b10 "
b10 '
b10 .
b10 8
b10 ?
b10 C
b10 G
b10 H
b10 I
1=
1/
1N
10
1E
12
1%
#375
0=
0/
0N
00
0E
02
0%
#380
b11 :
b11 @
b11 "
b11 '
b11 .
b11 8
b11 ?
b11 C
b11 G
b11 H
b11 I
1=
1/
1N
10
1E
12
1%
#385
0=
0/
0N
00
0E
02
0%
#390
0Q
1D
15
1L
1<
1K
1*
1#
11
16
1P
1=
1/
1N
10
1E
12
1%
0O
0,
0F
0-
0$
#395
0=
0/
0N
00
0E
02
0%
#400
0D
05
0L
0<
0K
0*
0#
01
06
0P
b11 !
b11 (
b11 7
b11 9
b11 >
b11 A
b11 B
0R
b0 :
b0 @
b0 "
b0 '
b0 .
b0 8
b0 ?
b0 C
b0 G
b0 H
b0 I
1=
1/
1N
10
1E
12
1%
#405
0=
0/
0N
00
0E
02
0%
#410
1=
1/
1N
10
1E
12
1%
#415
0=
0/
0N
00
0E
02
0%
#420
1=
1/
1N
10
1E
12
1%
#425
0=
0/
0N
00
0E
02
0%
#430
1=
1/
1N
10
1E
12
1%
#435
0=
0/
0N
00
0E
02
0%
#440
1=
1/
1N
10
1E
12
1%
#445
0=
0/
0N
00
0E
02
0%
#450
1=
1/
1N
10
1E
12
1%
#455
0=
0/
0N
00
0E
02
0%
#460
1=
1/
1N
10
1E
12
1%
#465
0=
0/
0N
00
0E
02
0%
#470
1=
1/
1N
10
1E
12
1%
#475
0=
0/
0N
00
0E
02
0%
#480
1=
1/
1N
10
1E
12
1%
#485
0=
0/
0N
00
0E
02
0%
#490
1=
1/
1N
10
1E
12
1%
#495
0=
0/
0N
00
0E
02
0%
#500
1=
1/
1N
10
1E
12
1%
#505
0=
0/
0N
00
0E
02
0%
#510
1=
1/
1N
10
1E
12
1%
#515
0=
0/
0N
00
0E
02
0%
#520
1=
1/
1N
10
1E
12
1%
#525
0=
0/
0N
00
0E
02
0%
#530
1=
1/
1N
10
1E
12
1%
#535
0=
0/
0N
00
0E
02
0%
#540
1=
1/
1N
10
1E
12
1%
#545
0=
0/
0N
00
0E
02
0%
#550
1=
1/
1N
10
1E
12
1%
#555
0=
0/
0N
00
0E
02
0%
#560
1=
1/
1N
10
1E
12
1%
#565
0=
0/
0N
00
0E
02
0%
#570
1=
1/
1N
10
1E
12
1%
#575
0=
0/
0N
00
0E
02
0%
#580
1=
1/
1N
10
1E
12
1%
#585
0=
0/
0N
00
0E
02
0%
#590
1=
1/
1N
10
1E
12
1%
#595
0=
0/
0N
00
0E
02
0%
#600
1=
1/
1N
10
1E
12
1%
#605
0=
0/
0N
00
0E
02
0%
#610
1=
1/
1N
10
1E
12
1%
#615
0=
0/
0N
00
0E
02
0%
#620
1=
1/
1N
10
1E
12
1%
#625
0=
0/
0N
00
0E
02
0%
#630
1=
1/
1N
10
1E
12
1%
#635
0=
0/
0N
00
0E
02
0%
#640
1=
1/
1N
10
1E
12
1%
#645
0=
0/
0N
00
0E
02
0%
#650
1=
1/
1N
10
1E
12
1%
#655
0=
0/
0N
00
0E
02
0%
#660
1=
1/
1N
10
1E
12
1%
#665
0=
0/
0N
00
0E
02
0%
#670
1=
1/
1N
10
1E
12
1%
#675
0=
0/
0N
00
0E
02
0%
#680
1=
1/
1N
10
1E
12
1%
#685
0=
0/
0N
00
0E
02
0%
#690
1=
1/
1N
10
1E
12
1%
#695
0=
0/
0N
00
0E
02
0%
#700
1=
1/
1N
10
1E
12
1%
#705
0=
0/
0N
00
0E
02
0%
#710
1=
1/
1N
10
1E
12
1%
#715
0=
0/
0N
00
0E
02
0%
#720
1=
1/
1N
10
1E
12
1%
#725
0=
0/
0N
00
0E
02
0%
#730
1=
1/
1N
10
1E
12
1%
#735
0=
0/
0N
00
0E
02
0%
#740
1=
1/
1N
10
1E
12
1%
#745
0=
0/
0N
00
0E
02
0%
#750
1=
1/
1N
10
1E
12
1%
#755
0=
0/
0N
00
0E
02
0%
#760
1=
1/
1N
10
1E
12
1%
#765
0=
0/
0N
00
0E
02
0%
#770
1=
1/
1N
10
1E
12
1%
#775
0=
0/
0N
00
0E
02
0%
#780
1=
1/
1N
10
1E
12
1%
#785
0=
0/
0N
00
0E
02
0%
#790
1=
1/
1N
10
1E
12
1%
#795
0=
0/
0N
00
0E
02
0%
#800
1=
1/
1N
10
1E
12
1%
#805
0=
0/
0N
00
0E
02
0%
#810
1=
1/
1N
10
1E
12
1%
#815
0=
0/
0N
00
0E
02
0%
#820
1=
1/
1N
10
1E
12
1%
#825
0=
0/
0N
00
0E
02
0%
#830
1=
1/
1N
10
1E
12
1%
#835
0=
0/
0N
00
0E
02
0%
#840
1=
1/
1N
10
1E
12
1%
#845
0=
0/
0N
00
0E
02
0%
#850
1=
1/
1N
10
1E
12
1%
#855
0=
0/
0N
00
0E
02
0%
#860
1=
1/
1N
10
1E
12
1%
#865
0=
0/
0N
00
0E
02
0%
#870
1=
1/
1N
10
1E
12
1%
#875
0=
0/
0N
00
0E
02
0%
#880
1=
1/
1N
10
1E
12
1%
#885
0=
0/
0N
00
0E
02
0%
#890
1=
1/
1N
10
1E
12
1%
#895
0=
0/
0N
00
0E
02
0%
#900
1=
1/
1N
10
1E
12
1%
#905
0=
0/
0N
00
0E
02
0%
#910
1=
1/
1N
10
1E
12
1%
#915
0=
0/
0N
00
0E
02
0%
#920
1=
1/
1N
10
1E
12
1%
#925
0=
0/
0N
00
0E
02
0%
#930
1=
1/
1N
10
1E
12
1%
#935
0=
0/
0N
00
0E
02
0%
#940
1=
1/
1N
10
1E
12
1%
#945
0=
0/
0N
00
0E
02
0%
#950
1=
1/
1N
10
1E
12
1%
#955
0=
0/
0N
00
0E
02
0%
#960
1=
1/
1N
10
1E
12
1%
#965
0=
0/
0N
00
0E
02
0%
#970
1=
1/
1N
10
1E
12
1%
#975
0=
0/
0N
00
0E
02
0%
#980
1=
1/
1N
10
1E
12
1%
#985
0=
0/
0N
00
0E
02
0%
#990
1=
1/
1N
10
1E
12
1%
#995
0=
0/
0N
00
0E
02
0%
#1000
1=
1/
1N
10
1E
12
1%
#1005
0=
0/
0N
00
0E
02
0%
#1010
1=
1/
1N
10
1E
12
1%
#1015
0=
0/
0N
00
0E
02
0%
#1020
1=
1/
1N
10
1E
12
1%
#1025
0=
0/
0N
00
0E
02
0%
#1030
1=
1/
1N
10
1E
12
1%
#1035
0=
0/
0N
00
0E
02
0%
#1040
1=
1/
1N
10
1E
12
1%
#1045
0=
0/
0N
00
0E
02
0%
#1050
1=
1/
1N
10
1E
12
1%
#1055
0=
0/
0N
00
0E
02
0%
#1060
1=
1/
1N
10
1E
12
1%
#1065
0=
0/
0N
00
0E
02
0%
#1070
1=
1/
1N
10
1E
12
1%
#1075
0=
0/
0N
00
0E
02
0%
#1080
1=
1/
1N
10
1E
12
1%
#1085
0=
0/
0N
00
0E
02
0%
#1090
1=
1/
1N
10
1E
12
1%
#1095
0=
0/
0N
00
0E
02
0%
#1100
1=
1/
1N
10
1E
12
1%
#1105
0=
0/
0N
00
0E
02
0%
#1110
1=
1/
1N
10
1E
12
1%
#1115
0=
0/
0N
00
0E
02
0%
#1120
1=
1/
1N
10
1E
12
1%
#1125
0=
0/
0N
00
0E
02
0%
#1130
1=
1/
1N
10
1E
12
1%
#1135
0=
0/
0N
00
0E
02
0%
#1140
1=
1/
1N
10
1E
12
1%
#1145
0=
0/
0N
00
0E
02
0%
#1150
1=
1/
1N
10
1E
12
1%
#1155
0=
0/
0N
00
0E
02
0%
#1160
1=
1/
1N
10
1E
12
1%
#1165
0=
0/
0N
00
0E
02
0%
#1170
1=
1/
1N
10
1E
12
1%
#1175
0=
0/
0N
00
0E
02
0%
#1180
1=
1/
1N
10
1E
12
1%
#1185
0=
0/
0N
00
0E
02
0%
#1190
1=
1/
1N
10
1E
12
1%
#1195
0=
0/
0N
00
0E
02
0%
#1200
1=
1/
1N
10
1E
12
1%
#1205
0=
0/
0N
00
0E
02
0%
#1210
1=
1/
1N
10
1E
12
1%
#1215
0=
0/
0N
00
0E
02
0%
#1220
1=
1/
1N
10
1E
12
1%
#1225
0=
0/
0N
00
0E
02
0%
#1230
1=
1/
1N
10
1E
12
1%
#1235
0=
0/
0N
00
0E
02
0%
#1240
1=
1/
1N
10
1E
12
1%
#1245
0=
0/
0N
00
0E
02
0%
#1250
1=
1/
1N
10
1E
12
1%
#1255
0=
0/
0N
00
0E
02
0%
#1260
1=
1/
1N
10
1E
12
1%
#1265
0=
0/
0N
00
0E
02
0%
#1270
1=
1/
1N
10
1E
12
1%
#1275
0=
0/
0N
00
0E
02
0%
#1280
1=
1/
1N
10
1E
12
1%
#1285
0=
0/
0N
00
0E
02
0%
#1290
1=
1/
1N
10
1E
12
1%
#1295
0=
0/
0N
00
0E
02
0%
#1300
1=
1/
1N
10
1E
12
1%
#1305
0=
0/
0N
00
0E
02
0%
#1310
1=
1/
1N
10
1E
12
1%
#1315
0=
0/
0N
00
0E
02
0%
#1320
1=
1/
1N
10
1E
12
1%
#1325
0=
0/
0N
00
0E
02
0%
#1330
1=
1/
1N
10
1E
12
1%
#1335
0=
0/
0N
00
0E
02
0%
#1340
1=
1/
1N
10
1E
12
1%
#1345
0=
0/
0N
00
0E
02
0%
#1350
1=
1/
1N
10
1E
12
1%
#1355
0=
0/
0N
00
0E
02
0%
#1360
1=
1/
1N
10
1E
12
1%
#1365
0=
0/
0N
00
0E
02
0%
#1370
1=
1/
1N
10
1E
12
1%
#1375
0=
0/
0N
00
0E
02
0%
#1380
1=
1/
1N
10
1E
12
1%
#1385
0=
0/
0N
00
0E
02
0%
#1390
1=
1/
1N
10
1E
12
1%
