Ice40/Curso Verilog/gtkwave/u(t) con reset/u(t).v
// Code generated by Icestudio 0.3.3
// Sat, 01 Dec 2018 20:54:12 GMT

`default_nettype none

module main #(
 parameter vf7cfab = 0
) (
 input vd3e926,
 input v4f007a,
 output vf23155,
 output [0:4] vinit
);
 localparam p1 = vf7cfab;
 wire w0;
 wire w2;
 wire w3;
 wire w4;
 wire w5;
 assign w2 = v4f007a;
 assign w3 = vd3e926;
 assign w4 = vd3e926;
 assign vf23155 = w5;
 assign w4 = w3;
 v7a1119 #(
  .va1edee(p1)
 ) v3f49ec (
  .v637c56(w0),
  .ve9fb46(w4),
  .v19bd79(w5)
 );
 vbc18a5 v81ccdf (
  .vba66dd(w0),
  .vdf6fc0(w2),
  .v038039(w3)
 );
 assign vinit = 5'b00000;
endmodule

module v7a1119 #(
 parameter va1edee = 0
) (
 input v637c56,
 input ve9fb46,
 output v19bd79
);
 localparam p1 = va1edee;
 wire w0;
 wire w2;
 wire w3;
 assign v19bd79 = w0;
 assign w2 = ve9fb46;
 assign w3 = v637c56;
 v7a1119_v8c8712 #(
  .t(p1)
 ) v8c8712 (
  .u(w0),
  .clk(w2),
  .reset(w3)
 );
endmodule

module v7a1119_v8c8712 #(
 parameter t = 0
) (
 input reset,
 input clk,
 output u
);
 // Escalón u(t)
 // t ciclos de reloj a 0 y
 // cambia a 1.
 
 localparam num_periods=t;
 
 reg[7:0] contador=0;
 reg u=1'b0;
 
 
 always @(posedge clk)
 if(reset) contador<=0;
 else if(contador >= num_periods-1)
  begin
  u <=1'b1;
  contador <= contador;
  end
 else
  begin
   u<=1'b0;
   contador=contador+1;
  end
  
  
  
  
endmodule

module vbc18a5 (
 input v038039,
 input vdf6fc0,
 output vba66dd
);
 wire w0;
 wire w1;
 wire w2;
 wire w3;
 wire w4;
 assign vba66dd = w1;
 assign w2 = vdf6fc0;
 assign w3 = v038039;
 assign w4 = v038039;
 assign w4 = w3;
 v8b89a5 v405f7d (
  .vc24d9f(w0),
  .vef4cea(w2),
  .vb55943(w3)
 );
 v8b89a5 v092af7 (
  .vef4cea(w0),
  .vc24d9f(w1),
  .vb55943(w4)
 );
endmodule

module v8b89a5 (
 input vb55943,
 input vef4cea,
 output vc24d9f
);
 wire w0;
 wire w1;
 wire w2;
 assign w0 = vef4cea;
 assign w1 = vb55943;
 assign vc24d9f = w2;
 v8b89a5_v526aa2 v526aa2 (
  .d(w0),
  .clk(w1),
  .q(w2)
 );
endmodule

module v8b89a5_v526aa2 (
 input clk,
 input d,
 output q
);
 // D flip-flop
 
 reg q = 1'b0;
 
 always @(posedge clk)
 begin
   q <= d;
 end
 
 
endmodule

Ice40/Curso Verilog/gtkwave/u(t) con reset/u(t)_tb.v
// Code generated by Icestudio 0.3.3
// Sat, 01 Dec 2018 20:54:29 GMT

// Testbench template

`default_nettype none
`define DUMPSTR(x) `"x.vcd`"
`timescale 10 ns / 1 ns


module main_tb
;
 
 // Simulation time: 100ns (10 * 10ns)
 parameter DURATION = 200;
 
 // TODO: edit the module parameters here
 // e.g. localparam constant_value = 1;
 localparam constant_Inicio_En =5 ;
 
 // Input/Output
 reg reloj;
 reg reset;
 wire escalon;
 
 // Module instance
 main #(
  .vf7cfab(constant_Inicio_En)
 ) MAIN (
  .vd3e926(reloj),
  .v4f007a(reset),
  .vf23155(escalon)
 );
 
 always #1 reloj=~reloj;        // Genero reloj
 
 initial begin
  // File were to store the simulation results
  $dumpfile(`DUMPSTR(`VCD_OUTPUT));
  $dumpvars(0, main_tb);
 
  // TODO: initialize the registers here
  // e.g. value = 1;
  // e.g. #2 value = 0;
  reloj = 0;
  reset = 0;
  #20 reset=1;
  #2 reset=0;
  #19 reset=1;
  #2  reset=0;
  #21 reset=1;
  #2  reset=0;
  
 
  #(DURATION) $display("End of simulation");
  $finish;
 end
 
endmodule

Ice40/Curso Verilog/gtkwave/u(t) con reset/u(t)_tb.vcd
$date
	Sat Dec 01 22:05:37 2018
$end
$version
	Icarus Verilog
$end
$timescale
	1ns
$end
$scope module main_tb $end
$var wire 1 ! escalon $end
$var reg 1 " reloj $end
$var reg 1 # reset $end
$scope module MAIN $end
$var wire 1 # v4f007a $end
$var wire 1 " vd3e926 $end
$var wire 1 ! vf23155 $end
$var wire 5 $ vinit [0:4] $end
$var wire 1 % w2 $end
$var wire 1 & w3 $end
$var wire 1 ' w4 $end
$var wire 1 ( w5 $end
$var wire 1 ) w0 $end
$scope module v3f49ec $end
$var wire 1 ( v19bd79 $end
$var wire 1 ' ve9fb46 $end
$var wire 1 * w2 $end
$var wire 1 + w3 $end
$var wire 1 , w0 $end
$var wire 1 ) v637c56 $end
$scope module v8c8712 $end
$var wire 1 * clk $end
$var wire 1 + reset $end
$var reg 8 - contador [7:0] $end
$var reg 1 , u $end
$upscope $end
$upscope $end
$scope module v81ccdf $end
$var wire 1 & v038039 $end
$var wire 1 ) vba66dd $end
$var wire 1 % vdf6fc0 $end
$var wire 1 . w2 $end
$var wire 1 / w3 $end
$var wire 1 0 w4 $end
$var wire 1 1 w1 $end
$var wire 1 2 w0 $end
$scope module v092af7 $end
$var wire 1 0 vb55943 $end
$var wire 1 1 vc24d9f $end
$var wire 1 3 w0 $end
$var wire 1 4 w1 $end
$var wire 1 5 w2 $end
$var wire 1 2 vef4cea $end
$scope module v526aa2 $end
$var wire 1 4 clk $end
$var wire 1 3 d $end
$var reg 1 5 q $end
$upscope $end
$upscope $end
$scope module v405f7d $end
$var wire 1 / vb55943 $end
$var wire 1 2 vc24d9f $end
$var wire 1 . vef4cea $end
$var wire 1 6 w0 $end
$var wire 1 7 w1 $end
$var wire 1 8 w2 $end
$scope module v526aa2 $end
$var wire 1 7 clk $end
$var wire 1 6 d $end
$var reg 1 8 q $end
$upscope $end
$upscope $end
$upscope $end
$upscope $end
$upscope $end
$enddefinitions $end
#0
$dumpvars
08
07
06
05
04
03
02
01
00
0/
0.
b0 -
0,
0+
0*
0)
0(
0'
0&
0%
b0 $
0#
0"
0!
$end
#10
b1 -
17
1/
14
10
1&
1*
1'
1"
#20
07
0/
04
00
0&
0*
0'
0"
#30
b10 -
17
1/
14
10
1&
1*
1'
1"
#40
07
0/
04
00
0&
0*
0'
0"
#50
b11 -
17
1/
14
10
1&
1*
1'
1"
#60
07
0/
04
00
0&
0*
0'
0"
#70
b100 -
17
1/
14
10
1&
1*
1'
1"
#80
07
0/
04
00
0&
0*
0'
0"
#90
1!
1(
1,
17
1/
14
10
1&
1*
1'
1"
#100
07
0/
04
00
0&
0*
0'
0"
#110
17
1/
14
10
1&
1*
1'
1"
#120
07
0/
04
00
0&
0*
0'
0"
#130
17
1/
14
10
1&
1*
1'
1"
#140
07
0/
04
00
0&
0*
0'
0"
#150
17
1/
14
10
1&
1*
1'
1"
#160
07
0/
04
00
0&
0*
0'
0"
#170
17
1/
14
10
1&
1*
1'
1"
#180
07
0/
04
00
0&
0*
0'
0"
#190
17
1/
14
10
1&
1*
1'
1"
#200
07
0/
04
00
0&
0*
0'
0"
16
1.
1%
1#
#210
13
12
18
17
1/
14
10
1&
1*
1'
1"
#220
07
0/
04
00
0&
0*
0'
0"
06
0.
0%
0#
#230
03
02
08
1+
1)
11
15
17
1/
14
10
1&
1*
1'
1"
#240
07
0/
04
00
0&
0*
0'
0"
#250
0+
0)
01
05
b0 -
17
1/
14
10
1&
1*
1'
1"
#260
07
0/
04
00
0&
0*
0'
0"
#270
0!
0(
0,
b1 -
17
1/
14
10
1&
1*
1'
1"
#280
07
0/
04
00
0&
0*
0'
0"
#290
b10 -
17
1/
14
10
1&
1*
1'
1"
#300
07
0/
04
00
0&
0*
0'
0"
#310
b11 -
17
1/
14
10
1&
1*
1'
1"
#320
07
0/
04
00
0&
0*
0'
0"
#330
b100 -
17
1/
14
10
1&
1*
1'
1"
#340
07
0/
04
00
0&
0*
0'
0"
#350
1!
1(
1,
17
1/
14
10
1&
1*
1'
1"
#360
07
0/
04
00
0&
0*
0'
0"
#370
17
1/
14
10
1&
1*
1'
1"
#380
07
0/
04
00
0&
0*
0'
0"
#390
17
1/
14
10
1&
1*
1'
1"
#400
07
0/
04
00
0&
0*
0'
0"
#410
13
12
18
17
1/
14
10
1&
1*
1'
1"
16
1.
1%
1#
#420
07
0/
04
00
0&
0*
0'
0"
#430
03
02
08
1+
1)
11
15
17
1/
14
10
1&
1*
1'
1"
06
0.
0%
0#
#440
07
0/
04
00
0&
0*
0'
0"
#450
0+
0)
01
05
b0 -
17
1/
14
10
1&
1*
1'
1"
#460
07
0/
04
00
0&
0*
0'
0"
#470
0!
0(
0,
b1 -
17
1/
14
10
1&
1*
1'
1"
#480
07
0/
04
00
0&
0*
0'
0"
#490
b10 -
17
1/
14
10
1&
1*
1'
1"
#500
07
0/
04
00
0&
0*
0'
0"
#510
b11 -
17
1/
14
10
1&
1*
1'
1"
#520
07
0/
04
00
0&
0*
0'
0"
#530
b100 -
17
1/
14
10
1&
1*
1'
1"
#540
07
0/
04
00
0&
0*
0'
0"
#550
1!
1(
1,
17
1/
14
10
1&
1*
1'
1"
#560
07
0/
04
00
0&
0*
0'
0"
#570
17
1/
14
10
1&
1*
1'
1"
#580
07
0/
04
00
0&
0*
0'
0"
#590
17
1/
14
10
1&
1*
1'
1"
#600
07
0/
04
00
0&
0*
0'
0"
#610
17
1/
14
10
1&
1*
1'
1"
#620
07
0/
04
00
0&
0*
0'
0"
#630
17
1/
14
10
1&
1*
1'
1"
#640
07
0/
04
00
0&
0*
0'
0"
16
1.
1%
1#
#650
13
12
18
17
1/
14
10
1&
1*
1'
1"
#660
07
0/
04
00
0&
0*
0'
0"
06
0.
0%
0#
#670
03
02
08
1+
1)
11
15
17
1/
14
10
1&
1*
1'
1"
#680
07
0/
04
00
0&
0*
0'
0"
#690
0+
0)
01
05
b0 -
17
1/
14
10
1&
1*
1'
1"
#700
07
0/
04
00
0&
0*
0'
0"
#710
0!
0(
0,
b1 -
17
1/
14
10
1&
1*
1'
1"
#720
07
0/
04
00
0&
0*
0'
0"
#730
b10 -
17
1/
14
10
1&
1*
1'
1"
#740
07
0/
04
00
0&
0*
0'
0"
#750
b11 -
17
1/
14
10
1&
1*
1'
1"
#760
07
0/
04
00
0&
0*
0'
0"
#770
b100 -
17
1/
14
10
1&
1*
1'
1"
#780
07
0/
04
00
0&
0*
0'
0"
#790
1!
1(
1,
17
1/
14
10
1&
1*
1'
1"
#800
07
0/
04
00
0&
0*
0'
0"
#810
17
1/
14
10
1&
1*
1'
1"
#820
07
0/
04
00
0&
0*
0'
0"
#830
17
1/
14
10
1&
1*
1'
1"
#840
07
0/
04
00
0&
0*
0'
0"
#850
17
1/
14
10
1&
1*
1'
1"
#860
07
0/
04
00
0&
0*
0'
0"
#870
17
1/
14
10
1&
1*
1'
1"
#880
07
0/
04
00
0&
0*
0'
0"
#890
17
1/
14
10
1&
1*
1'
1"
#900
07
0/
04
00
0&
0*
0'
0"
#910
17
1/
14
10
1&
1*
1'
1"
#920
07
0/
04
00
0&
0*
0'
0"
#930
17
1/
14
10
1&
1*
1'
1"
#940
07
0/
04
00
0&
0*
0'
0"
#950
17
1/
14
10
1&
1*
1'
1"
#960
07
0/
04
00
0&
0*
0'
0"
#970
17
1/
14
10
1&
1*
1'
1"
#980
07
0/
04
00
0&
0*
0'
0"
#990
17
1/
14
10
1&
1*
1'
1"
#1000
07
0/
04
00
0&
0*
0'
0"
#1010
17
1/
14
10
1&
1*
1'
1"
#1020
07
0/
04
00
0&
0*
0'
0"
#1030
17
1/
14
10
1&
1*
1'
1"
#1040
07
0/
04
00
0&
0*
0'
0"
#1050
17
1/
14
10
1&
1*
1'
1"
#1060
07
0/
04
00
0&
0*
0'
0"
#1070
17
1/
14
10
1&
1*
1'
1"
#1080
07
0/
04
00
0&
0*
0'
0"
#1090
17
1/
14
10
1&
1*
1'
1"
#1100
07
0/
04
00
0&
0*
0'
0"
#1110
17
1/
14
10
1&
1*
1'
1"
#1120
07
0/
04
00
0&
0*
0'
0"
#1130
17
1/
14
10
1&
1*
1'
1"
#1140
07
0/
04
00
0&
0*
0'
0"
#1150
17
1/
14
10
1&
1*
1'
1"
#1160
07
0/
04
00
0&
0*
0'
0"
#1170
17
1/
14
10
1&
1*
1'
1"
#1180
07
0/
04
00
0&
0*
0'
0"
#1190
17
1/
14
10
1&
1*
1'
1"
#1200
07
0/
04
00
0&
0*
0'
0"
#1210
17
1/
14
10
1&
1*
1'
1"
#1220
07
0/
04
00
0&
0*
0'
0"
#1230
17
1/
14
10
1&
1*
1'
1"
#1240
07
0/
04
00
0&
0*
0'
0"
#1250
17
1/
14
10
1&
1*
1'
1"
#1260
07
0/
04
00
0&
0*
0'
0"
#1270
17
1/
14
10
1&
1*
1'
1"
#1280
07
0/
04
00
0&
0*
0'
0"
#1290
17
1/
14
10
1&
1*
1'
1"
#1300
07
0/
04
00
0&
0*
0'
0"
#1310
17
1/
14
10
1&
1*
1'
1"
#1320
07
0/
04
00
0&
0*
0'
0"
#1330
17
1/
14
10
1&
1*
1'
1"
#1340
07
0/
04
00
0&
0*
0'
0"
#1350
17
1/
14
10
1&
1*
1'
1"
#1360
07
0/
04
00
0&
0*
0'
0"
#1370
17
1/
14
10
1&
1*
1'
1"
#1380
07
0/
04
00
0&
0*
0'
0"
#1390
17
1/
14
10
1&
1*
1'
1"
#1400
07
0/
04
00
0&
0*
0'
0"
#1410
17
1/
14
10
1&
1*
1'
1"
#1420
07
0/
04
00
0&
0*
0'
0"
#1430
17
1/
14
10
1&
1*
1'
1"
#1440
07
0/
04
00
0&
0*
0'
0"
#1450
17
1/
14
10
1&
1*
1'
1"
#1460
07
0/
04
00
0&
0*
0'
0"
#1470
17
1/
14
10
1&
1*
1'
1"
#1480
07
0/
04
00
0&
0*
0'
0"
#1490
17
1/
14
10
1&
1*
1'
1"
#1500
07
0/
04
00
0&
0*
0'
0"
#1510
17
1/
14
10
1&
1*
1'
1"
#1520
07
0/
04
00
0&
0*
0'
0"
#1530
17
1/
14
10
1&
1*
1'
1"
#1540
07
0/
04
00
0&
0*
0'
0"
#1550
17
1/
14
10
1&
1*
1'
1"
#1560
07
0/
04
00
0&
0*
0'
0"
#1570
17
1/
14
10
1&
1*
1'
1"
#1580
07
0/
04
00
0&
0*
0'
0"
#1590
17
1/
14
10
1&
1*
1'
1"
#1600
07
0/
04
00
0&
0*
0'
0"
#1610
17
1/
14
10
1&
1*
1'
1"
#1620
07
0/
04
00
0&
0*
0'
0"
#1630
17
1/
14
10
1&
1*
1'
1"
#1640
07
0/
04
00
0&
0*
0'
0"
#1650
17
1/
14
10
1&
1*
1'
1"
#1660
07
0/
04
00
0&
0*
0'
0"
#1670
17
1/
14
10
1&
1*
1'
1"
#1680
07
0/
04
00
0&
0*
0'
0"
#1690
17
1/
14
10
1&
1*
1'
1"
#1700
07
0/
04
00
0&
0*
0'
0"
#1710
17
1/
14
10
1&
1*
1'
1"
#1720
07
0/
04
00
0&
0*
0'
0"
#1730
17
1/
14
10
1&
1*
1'
1"
#1740
07
0/
04
00
0&
0*
0'
0"
#1750
17
1/
14
10
1&
1*
1'
1"
#1760
07
0/
04
00
0&
0*
0'
0"
#1770
17
1/
14
10
1&
1*
1'
1"
#1780
07
0/
04
00
0&
0*
0'
0"
#1790
17
1/
14
10
1&
1*
1'
1"
#1800
07
0/
04
00
0&
0*
0'
0"
#1810
17
1/
14
10
1&
1*
1'
1"
#1820
07
0/
04
00
0&
0*
0'
0"
#1830
17
1/
14
10
1&
1*
1'
1"
#1840
07
0/
04
00
0&
0*
0'
0"
#1850
17
1/
14
10
1&
1*
1'
1"
#1860
07
0/
04
00
0&
0*
0'
0"
#1870
17
1/
14
10
1&
1*
1'
1"
#1880
07
0/
04
00
0&
0*
0'
0"
#1890
17
1/
14
10
1&
1*
1'
1"
#1900
07
0/
04
00
0&
0*
0'
0"
#1910
17
1/
14
10
1&
1*
1'
1"
#1920
07
0/
04
00
0&
0*
0'
0"
#1930
17
1/
14
10
1&
1*
1'
1"
#1940
07
0/
04
00
0&
0*
0'
0"
#1950
17
1/
14
10
1&
1*
1'
1"
#1960
07
0/
04
00
0&
0*
0'
0"
#1970
17
1/
14
10
1&
1*
1'
1"
#1980
07
0/
04
00
0&
0*
0'
0"
#1990
17
1/
14
10
1&
1*
1'
1"
#2000
07
0/
04
00
0&
0*
0'
0"
#2010
17
1/
14
10
1&
1*
1'
1"
#2020
07
0/
04
00
0&
0*
0'
0"
#2030
17
1/
14
10
1&
1*
1'
1"
#2040
07
0/
04
00
0&
0*
0'
0"
#2050
17
1/
14
10
1&
1*
1'
1"
#2060
07
0/
04
00
0&
0*
0'
0"
#2070
17
1/
14
10
1&
1*
1'
1"
#2080
07
0/
04
00
0&
0*
0'
0"
#2090
17
1/
14
10
1&
1*
1'
1"
#2100
07
0/
04
00
0&
0*
0'
0"
#2110
17
1/
14
10
1&
1*
1'
1"
#2120
07
0/
04
00
0&
0*
0'
0"
#2130
17
1/
14
10
1&
1*
1'
1"
#2140
07
0/
04
00
0&
0*
0'
0"
#2150
17
1/
14
10
1&
1*
1'
1"
#2160
07
0/
04
00
0&
0*
0'
0"
#2170
17
1/
14
10
1&
1*
1'
1"
#2180
07
0/
04
00
0&
0*
0'
0"
#2190
17
1/
14
10
1&
1*
1'
1"
#2200
07
0/
04
00
0&
0*
0'
0"
#2210
17
1/
14
10
1&
1*
1'
1"
#2220
07
0/
04
00
0&
0*
0'
0"
#2230
17
1/
14
10
1&
1*
1'
1"
#2240
07
0/
04
00
0&
0*
0'
0"
#2250
17
1/
14
10
1&
1*
1'
1"
#2260
07
0/
04
00
0&
0*
0'
0"
#2270
17
1/
14
10
1&
1*
1'
1"
#2280
07
0/
04
00
0&
0*
0'
0"
#2290
17
1/
14
10
1&
1*
1'
1"
#2300
07
0/
04
00
0&
0*
0'
0"
#2310
17
1/
14
10
1&
1*
1'
1"
#2320
07
0/
04
00
0&
0*
0'
0"
#2330
17
1/
14
10
1&
1*
1'
1"
#2340
07
0/
04
00
0&
0*
0'
0"
#2350
17
1/
14
10
1&
1*
1'
1"
#2360
07
0/
04
00
0&
0*
0'
0"
#2370
17
1/
14
10
1&
1*
1'
1"
#2380
07
0/
04
00
0&
0*
0'
0"
#2390
17
1/
14
10
1&
1*
1'
1"
#2400
07
0/
04
00
0&
0*
0'
0"
#2410
17
1/
14
10
1&
1*
1'
1"
#2420
07
0/
04
00
0&
0*
0'
0"
#2430
17
1/
14
10
1&
1*
1'
1"
#2440
07
0/
04
00
0&
0*
0'
0"
#2450
17
1/
14
10
1&
1*
1'
1"
#2460
07
0/
04
00
0&
0*
0'
0"
#2470
17
1/
14
10
1&
1*
1'
1"
#2480
07
0/
04
00
0&
0*
0'
0"
#2490
17
1/
14
10
1&
1*
1'
1"
#2500
07
0/
04
00
0&
0*
0'
0"
#2510
17
1/
14
10
1&
1*
1'
1"
#2520
07
0/
04
00
0&
0*
0'
0"
#2530
17
1/
14
10
1&
1*
1'
1"
#2540
07
0/
04
00
0&
0*
0'
0"
#2550
17
1/
14
10
1&
1*
1'
1"
#2560
07
0/
04
00
0&
0*
0'
0"
#2570
17
1/
14
10
1&
1*
1'
1"
#2580
07
0/
04
00
0&
0*
0'
0"
#2590
17
1/
14
10
1&
1*
1'
1"
#2600
07
0/
04
00
0&
0*
0'
0"
#2610
17
1/
14
10
1&
1*
1'
1"
#2620
07
0/
04
00
0&
0*
0'
0"
#2630
17
1/
14
10
1&
1*
1'
1"
#2640
07
0/
04
00
0&
0*
0'
0"
#2650
17
1/
14
10
1&
1*
1'
1"
#2660
07
0/
04
00
0&
0*
0'
0"
