Ice40/Modulos/Pulso/Tics/gtkwave/Rising_Modo2/Rising_Modo2_Test_.v
// Code generated by Icestudio 0.3.3
// Sun, 02 Dec 2018 23:41:04 GMT

`default_nettype none

module main (
 input va1feb1,
 input v4e5c9f,
 input vc9fba8,
 output vd9fe63,
 output [0:4] vinit
);
 wire w0;
 wire w1;
 wire w2;
 wire w3;
 assign w0 = va1feb1;
 assign vd9fe63 = w1;
 assign w2 = v4e5c9f;
 assign w3 = vc9fba8;
 v92a3ca v7432ea (
  .v02d455(w0),
  .v32443d(w1),
  .v4ae82c(w2),
  .v08bfd6(w3)
 );
 assign vinit = 5'b00000;
endmodule

module v92a3ca (
 input v02d455,
 input v4ae82c,
 input v08bfd6,
 output v32443d
);
 wire w0;
 wire w1;
 wire w2;
 wire w3;
 assign v32443d = w0;
 assign w1 = v02d455;
 assign w2 = v4ae82c;
 assign w3 = v08bfd6;
 v92a3ca_v3523b6 v3523b6 (
  .Rising(w0),
  .clk(w1),
  .reset(w2),
  .in(w3)
 );
endmodule

module v92a3ca_v3523b6 (
 input clk,
 input reset,
 input in,
 output Rising
);
 
 reg Q1=0,Q2=0;
 
 //Biestable D donde capturo estado actual (in) y anterior (Q)
 always @(posedge clk)
 if(reset)
    begin
     Q1<=1'b1;
     Q2<=1'b1;
    end 
 else
    begin
      Q1<=in;
      Q2<=Q1;
    end
      
 
 //Con datos del estado actual ya anterior, realizando un circutio combinacional
 //puedo saber si la señal a cambiado y si ha subido o ha bajado el flanco.
 
 assign Rising  = (in & ~Q2) & ~reset; // Si in (Actual) es 1 pero antes (Q) era 0 --> Rising
endmodule

Ice40/Modulos/Pulso/Tics/gtkwave/Rising_Modo2/Rising_Modo2_Test__tb.v
// Code generated by Icestudio 0.3.3
// Sun, 02 Dec 2018 23:08:46 GMT

// Testbench template

`default_nettype none
`define DUMPSTR(x) `"x.vcd`"
`timescale 10 ns / 1 ns


module main_tb
;
 
 // Simulation time: 100ns (10 * 10ns)
 parameter DURATION = 100;
 
 // Input/Output
 reg clk;
 reg reset;
 reg in;
 wire Rising;
 
 // Module instance
 main MAIN (
  .va1feb1(clk),
  .v4e5c9f(reset),
  .vc9fba8(in),
  .vd9fe63(Rising)
 );
 
 // Clock signal
 always #0.5 clk = ~clk;
 
 initial begin
  // File were to store the simulation results
  $dumpfile(`DUMPSTR(`VCD_OUTPUT));
  $dumpvars(0, main_tb);
 
  // TODO: initialize the registers here
  // e.g. value = 1;
  // e.g. #2 value = 0;
  clk = 1;
  reset = 0;
  in = 0;
  #4 in=1;
  #5 in=0;
  #3 in=1;
  #1 in=0;
  #7 in=1;
  #1 reset=1;
  #1 reset=0;
  #4 in=0;
  
 
  #(DURATION) $display("End of simulation");
  $finish;
 end
 
endmodule

Ice40/Modulos/Pulso/Tics/gtkwave/Rising_Modo2/Rising_Modo2_Test__tb.vcd
$date
	Mon Dec 03 00:41:19 2018
$end
$version
	Icarus Verilog
$end
$timescale
	1ns
$end
$scope module main_tb $end
$var wire 1 ! Rising $end
$var reg 1 " clk $end
$var reg 1 # in $end
$var reg 1 $ reset $end
$scope module MAIN $end
$var wire 1 $ v4e5c9f $end
$var wire 1 " va1feb1 $end
$var wire 1 # vc9fba8 $end
$var wire 1 ! vd9fe63 $end
$var wire 5 % vinit [0:4] $end
$var wire 1 & w0 $end
$var wire 1 ' w2 $end
$var wire 1 ( w3 $end
$var wire 1 ) w1 $end
$scope module v7432ea $end
$var wire 1 & v02d455 $end
$var wire 1 ( v08bfd6 $end
$var wire 1 ) v32443d $end
$var wire 1 ' v4ae82c $end
$var wire 1 * w1 $end
$var wire 1 + w2 $end
$var wire 1 , w3 $end
$var wire 1 - w0 $end
$scope module v3523b6 $end
$var wire 1 - Rising $end
$var wire 1 * clk $end
$var wire 1 , in $end
$var wire 1 + reset $end
$var reg 1 . Q1 $end
$var reg 1 / Q2 $end
$upscope $end
$upscope $end
$upscope $end
$upscope $end
$enddefinitions $end
#0
$dumpvars
0/
0.
0-
0,
0+
1*
0)
0(
0'
1&
b0 %
0$
0#
1"
0!
$end
#5
0*
0&
0"
#10
1*
1&
1"
#15
0*
0&
0"
#20
1*
1&
1"
#25
0*
0&
0"
#30
1*
1&
1"
#35
0*
0&
0"
#40
1.
1!
1)
1-
1*
1&
1"
1,
1(
1#
#45
0*
0&
0"
#50
0!
0)
0-
1/
1*
1&
1"
#55
0*
0&
0"
#60
1*
1&
1"
#65
0*
0&
0"
#70
1*
1&
1"
#75
0*
0&
0"
#80
1*
1&
1"
#85
0*
0&
0"
#90
0.
1*
1&
1"
0,
0(
0#
#95
0*
0&
0"
#100
0/
1*
1&
1"
#105
0*
0&
0"
#110
1*
1&
1"
#115
0*
0&
0"
#120
1.
1!
1)
1-
1*
1&
1"
1,
1(
1#
#125
0*
0&
0"
#130
1/
0.
0!
0)
0-
1*
1&
1"
0,
0(
0#
#135
0*
0&
0"
#140
0/
1*
1&
1"
#145
0*
0&
0"
#150
1*
1&
1"
#155
0*
0&
0"
#160
1*
1&
1"
#165
0*
0&
0"
#170
1*
1&
1"
#175
0*
0&
0"
#180
1*
1&
1"
#185
0*
0&
0"
#190
1*
1&
1"
#195
0*
0&
0"
#200
1.
1!
1)
1-
1*
1&
1"
1,
1(
1#
#205
0*
0&
0"
#210
1/
0!
0)
0-
1*
1&
1"
1+
1'
1$
#215
0*
0&
0"
#220
1*
1&
1"
0+
0'
0$
#225
0*
0&
0"
#230
1*
1&
1"
#235
0*
0&
0"
#240
1*
1&
1"
#245
0*
0&
0"
#250
1*
1&
1"
#255
0*
0&
0"
#260
0.
1*
1&
1"
0,
0(
0#
#265
0*
0&
0"
#270
0/
1*
1&
1"
#275
0*
0&
0"
#280
1*
1&
1"
#285
0*
0&
0"
#290
1*
1&
1"
#295
0*
0&
0"
#300
1*
1&
1"
#305
0*
0&
0"
#310
1*
1&
1"
#315
0*
0&
0"
#320
1*
1&
1"
#325
0*
0&
0"
#330
1*
1&
1"
#335
0*
0&
0"
#340
1*
1&
1"
#345
0*
0&
0"
#350
1*
1&
1"
#355
0*
0&
0"
#360
1*
1&
1"
#365
0*
0&
0"
#370
1*
1&
1"
#375
0*
0&
0"
#380
1*
1&
1"
#385
0*
0&
0"
#390
1*
1&
1"
#395
0*
0&
0"
#400
1*
1&
1"
#405
0*
0&
0"
#410
1*
1&
1"
#415
0*
0&
0"
#420
1*
1&
1"
#425
0*
0&
0"
#430
1*
1&
1"
#435
0*
0&
0"
#440
1*
1&
1"
#445
0*
0&
0"
#450
1*
1&
1"
#455
0*
0&
0"
#460
1*
1&
1"
#465
0*
0&
0"
#470
1*
1&
1"
#475
0*
0&
0"
#480
1*
1&
1"
#485
0*
0&
0"
#490
1*
1&
1"
#495
0*
0&
0"
#500
1*
1&
1"
#505
0*
0&
0"
#510
1*
1&
1"
#515
0*
0&
0"
#520
1*
1&
1"
#525
0*
0&
0"
#530
1*
1&
1"
#535
0*
0&
0"
#540
1*
1&
1"
#545
0*
0&
0"
#550
1*
1&
1"
#555
0*
0&
0"
#560
1*
1&
1"
#565
0*
0&
0"
#570
1*
1&
1"
#575
0*
0&
0"
#580
1*
1&
1"
#585
0*
0&
0"
#590
1*
1&
1"
#595
0*
0&
0"
#600
1*
1&
1"
#605
0*
0&
0"
#610
1*
1&
1"
#615
0*
0&
0"
#620
1*
1&
1"
#625
0*
0&
0"
#630
1*
1&
1"
#635
0*
0&
0"
#640
1*
1&
1"
#645
0*
0&
0"
#650
1*
1&
1"
#655
0*
0&
0"
#660
1*
1&
1"
#665
0*
0&
0"
#670
1*
1&
1"
#675
0*
0&
0"
#680
1*
1&
1"
#685
0*
0&
0"
#690
1*
1&
1"
#695
0*
0&
0"
#700
1*
1&
1"
#705
0*
0&
0"
#710
1*
1&
1"
#715
0*
0&
0"
#720
1*
1&
1"
#725
0*
0&
0"
#730
1*
1&
1"
#735
0*
0&
0"
#740
1*
1&
1"
#745
0*
0&
0"
#750
1*
1&
1"
#755
0*
0&
0"
#760
1*
1&
1"
#765
0*
0&
0"
#770
1*
1&
1"
#775
0*
0&
0"
#780
1*
1&
1"
#785
0*
0&
0"
#790
1*
1&
1"
#795
0*
0&
0"
#800
1*
1&
1"
#805
0*
0&
0"
#810
1*
1&
1"
#815
0*
0&
0"
#820
1*
1&
1"
#825
0*
0&
0"
#830
1*
1&
1"
#835
0*
0&
0"
#840
1*
1&
1"
#845
0*
0&
0"
#850
1*
1&
1"
#855
0*
0&
0"
#860
1*
1&
1"
#865
0*
0&
0"
#870
1*
1&
1"
#875
0*
0&
0"
#880
1*
1&
1"
#885
0*
0&
0"
#890
1*
1&
1"
#895
0*
0&
0"
#900
1*
1&
1"
#905
0*
0&
0"
#910
1*
1&
1"
#915
0*
0&
0"
#920
1*
1&
1"
#925
0*
0&
0"
#930
1*
1&
1"
#935
0*
0&
0"
#940
1*
1&
1"
#945
0*
0&
0"
#950
1*
1&
1"
#955
0*
0&
0"
#960
1*
1&
1"
#965
0*
0&
0"
#970
1*
1&
1"
#975
0*
0&
0"
#980
1*
1&
1"
#985
0*
0&
0"
#990
1*
1&
1"
#995
0*
0&
0"
#1000
1*
1&
1"
#1005
0*
0&
0"
#1010
1*
1&
1"
#1015
0*
0&
0"
#1020
1*
1&
1"
#1025
0*
0&
0"
#1030
1*
1&
1"
#1035
0*
0&
0"
#1040
1*
1&
1"
#1045
0*
0&
0"
#1050
1*
1&
1"
#1055
0*
0&
0"
#1060
1*
1&
1"
#1065
0*
0&
0"
#1070
1*
1&
1"
#1075
0*
0&
0"
#1080
1*
1&
1"
#1085
0*
0&
0"
#1090
1*
1&
1"
#1095
0*
0&
0"
#1100
1*
1&
1"
#1105
0*
0&
0"
#1110
1*
1&
1"
#1115
0*
0&
0"
#1120
1*
1&
1"
#1125
0*
0&
0"
#1130
1*
1&
1"
#1135
0*
0&
0"
#1140
1*
1&
1"
#1145
0*
0&
0"
#1150
1*
1&
1"
#1155
0*
0&
0"
#1160
1*
1&
1"
#1165
0*
0&
0"
#1170
1*
1&
1"
#1175
0*
0&
0"
#1180
1*
1&
1"
#1185
0*
0&
0"
#1190
1*
1&
1"
#1195
0*
0&
0"
#1200
1*
1&
1"
#1205
0*
0&
0"
#1210
1*
1&
1"
#1215
0*
0&
0"
#1220
1*
1&
1"
#1225
0*
0&
0"
#1230
1*
1&
1"
#1235
0*
0&
0"
#1240
1*
1&
1"
#1245
0*
0&
0"
#1250
1*
1&
1"
#1255
0*
0&
0"
#1260
1*
1&
1"
