Ice40/PID/Modules/gtkwave/pulseFromToWreset/pulseFromToWreset.v
// Code generated by Icestudio 0.3.3
// Sat, 01 Dec 2018 22:05:26 GMT

`default_nettype none

module main #(
 parameter v522332 = 4,
 parameter vcfa10a = 8
) (
 input v9a92d6,
 input vfe0d1c,
 output v244f0f,
 output [0:4] vinit
);
 localparam p0 = v522332;
 localparam p1 = vcfa10a;
 wire w2;
 wire w3;
 wire w4;
 assign v244f0f = w2;
 assign w3 = v9a92d6;
 assign w4 = vfe0d1c;
 v46b691 #(
  .v2b07d6(p0),
  .v4dd05a(p1)
 ) v4ead26 (
  .vd67ea4(w2),
  .vf8ab06(w3),
  .v3f7fd6(w4)
 );
 assign vinit = 5'b00000;
endmodule

module v46b691 #(
 parameter v2b07d6 = 0,
 parameter v4dd05a = 0
) (
 input vf8ab06,
 input v3f7fd6,
 output vd67ea4
);
 localparam p1 = v2b07d6;
 localparam p4 = v4dd05a;
 wire w0;
 wire w2;
 wire w3;
 wire w5;
 wire w6;
 wire w7;
 wire w8;
 assign vd67ea4 = w0;
 assign w3 = v3f7fd6;
 assign w5 = v3f7fd6;
 assign w7 = vf8ab06;
 assign w8 = vf8ab06;
 assign w5 = w3;
 assign w8 = w7;
 v161240 vb8f207 (
  .vcbab45(w0),
  .v0e28cb(w2),
  .v3ca442(w6)
 );
 v94027a #(
  .va1edee(p4)
 ) vd220e9 (
  .ve9fb46(w5),
  .v19bd79(w6),
  .vdb65bd(w8)
 );
 v7a1119 #(
  .va1edee(p1)
 ) v94fb85 (
  .v19bd79(w2),
  .ve9fb46(w3),
  .v637c56(w7)
 );
endmodule

module v161240 (
 input v0e28cb,
 input v3ca442,
 output vcbab45
);
 wire w0;
 wire w1;
 wire w2;
 assign w0 = v0e28cb;
 assign w1 = v3ca442;
 assign vcbab45 = w2;
 v161240_vf4938a vf4938a (
  .a(w0),
  .b(w1),
  .c(w2)
 );
endmodule

module v161240_vf4938a (
 input a,
 input b,
 output c
);
 //-- Puerta AND
 
 assign c = a & b;
 
 
endmodule

module v94027a #(
 parameter va1edee = 0
) (
 input vdb65bd,
 input ve9fb46,
 output v19bd79
);
 localparam p1 = va1edee;
 wire w0;
 wire w2;
 wire w3;
 assign v19bd79 = w0;
 assign w2 = ve9fb46;
 assign w3 = vdb65bd;
 v94027a_v8c8712 #(
  .t(p1)
 ) v8c8712 (
  .u(w0),
  .clk(w2),
  .reset(w3)
 );
endmodule

module v94027a_v8c8712 #(
 parameter t = 0
) (
 input reset,
 input clk,
 output u
);
 // falling pulse in t
 // t ciclos de reloj a 1 y
 // cambia a 0.
 
 localparam num_periods=t;
 
 reg[7:0] contador=0;
 reg u=1'b1;
 
 
 always @(posedge clk)
 if(reset) contador<=0;
 else if(contador >= num_periods-1)
  begin
  u <=1'b0;
  contador <= contador;
  end
 else
  begin
   u<=1'b1;
   contador=contador+1;
  end
  
  
  
  
endmodule

module v7a1119 #(
 parameter va1edee = 0
) (
 input v637c56,
 input ve9fb46,
 output v19bd79
);
 localparam p1 = va1edee;
 wire w0;
 wire w2;
 wire w3;
 assign v19bd79 = w0;
 assign w2 = ve9fb46;
 assign w3 = v637c56;
 v7a1119_v8c8712 #(
  .t(p1)
 ) v8c8712 (
  .u(w0),
  .clk(w2),
  .reset(w3)
 );
endmodule

module v7a1119_v8c8712 #(
 parameter t = 0
) (
 input reset,
 input clk,
 output u
);
 // Escalón u(t)
 // t ciclos de reloj a 0 y
 // cambia a 1.
 
 localparam num_periods=t;
 
 reg[7:0] contador=0;
 reg u=1'b0;
 
 
 always @(posedge clk)
 if(reset) contador<=0;
 else if(contador >= num_periods-1)
  begin
  u <=1'b1;
  contador <= contador;
  end
 else
  begin
   u<=1'b0;
   contador=contador+1;
  end
  
  
  
  
endmodule

Ice40/PID/Modules/gtkwave/pulseFromToWreset/pulseFromToWreset_tb.v
// Code generated by Icestudio 0.3.3
// Sat, 01 Dec 2018 22:05:40 GMT

// Testbench template

`default_nettype none
`define DUMPSTR(x) `"x.vcd`"
`timescale 10 ns / 1 ns


module main_tb
;
 
 // Simulation time: 100ns (10 * 10ns)
 parameter DURATION = 100;
 
 // TODO: edit the module parameters here
 // e.g. localparam constant_value = 1;
 localparam constant_Start = 4;
 localparam constant_End = 8;
 
 // Input/Output
 reg reset;
 reg reloj;
 wire pulse;
 
 // Module instance
 main #(
  .v522332(constant_Start),
  .vcfa10a(constant_End)
 ) MAIN (
  .v9a92d6(reset),
  .vfe0d1c(reloj),
  .v244f0f(pulse)
 );
 
 always #1 reloj=~reloj;
 
 initial begin
  // File were to store the simulation results
  $dumpfile(`DUMPSTR(`VCD_OUTPUT));
  $dumpvars(0, main_tb);
 
  // TODO: initialize the registers here
  // e.g. value = 1;
  // e.g. #2 value = 0;
  reset = 0;
  reloj = 1;
  #20 reset=1;
  #2  reset=0;
  #19 reset=1;
  #2  reset=0;
  #21 reset=1;
  #2  reset=0;
  
 
  #(DURATION) $display("End of simulation");
  $finish;
 end
 
endmodule

Ice40/PID/Modules/gtkwave/pulseFromToWreset/pulseFromToWreset_tb.vcd
$date
	Sat Dec 01 23:10:53 2018
$end
$version
	Icarus Verilog
$end
$timescale
	1ns
$end
$scope module main_tb $end
$var wire 1 ! pulse $end
$var reg 1 " reloj $end
$var reg 1 # reset $end
$scope module MAIN $end
$var wire 1 ! v244f0f $end
$var wire 1 # v9a92d6 $end
$var wire 1 " vfe0d1c $end
$var wire 5 $ vinit [0:4] $end
$var wire 1 % w3 $end
$var wire 1 & w4 $end
$var wire 1 ' w2 $end
$scope module v4ead26 $end
$var wire 1 & v3f7fd6 $end
$var wire 1 ' vd67ea4 $end
$var wire 1 % vf8ab06 $end
$var wire 1 ( w3 $end
$var wire 1 ) w5 $end
$var wire 1 * w7 $end
$var wire 1 + w8 $end
$var wire 1 , w6 $end
$var wire 1 - w2 $end
$var wire 1 . w0 $end
$scope module v94fb85 $end
$var wire 1 - v19bd79 $end
$var wire 1 * v637c56 $end
$var wire 1 ( ve9fb46 $end
$var wire 1 / w2 $end
$var wire 1 0 w3 $end
$var wire 1 1 w0 $end
$scope module v8c8712 $end
$var wire 1 / clk $end
$var wire 1 0 reset $end
$var reg 8 2 contador [7:0] $end
$var reg 1 1 u $end
$upscope $end
$upscope $end
$scope module vb8f207 $end
$var wire 1 - v0e28cb $end
$var wire 1 . vcbab45 $end
$var wire 1 3 w0 $end
$var wire 1 4 w1 $end
$var wire 1 5 w2 $end
$var wire 1 , v3ca442 $end
$scope module vf4938a $end
$var wire 1 3 a $end
$var wire 1 4 b $end
$var wire 1 5 c $end
$upscope $end
$upscope $end
$scope module vd220e9 $end
$var wire 1 , v19bd79 $end
$var wire 1 + vdb65bd $end
$var wire 1 ) ve9fb46 $end
$var wire 1 6 w2 $end
$var wire 1 7 w3 $end
$var wire 1 8 w0 $end
$scope module v8c8712 $end
$var wire 1 6 clk $end
$var wire 1 7 reset $end
$var reg 8 9 contador [7:0] $end
$var reg 1 8 u $end
$upscope $end
$upscope $end
$upscope $end
$upscope $end
$upscope $end
$enddefinitions $end
#0
$dumpvars
b1 9
18
07
16
05
14
03
b1 2
01
00
1/
0.
0-
1,
0+
0*
1)
1(
0'
1&
0%
b0 $
0#
1"
0!
$end
#10
0/
0(
06
0)
0&
0"
#20
b10 2
b10 9
1/
1(
16
1)
1&
1"
#30
0/
0(
06
0)
0&
0"
#40
b11 2
b11 9
1/
1(
16
1)
1&
1"
#50
0/
0(
06
0)
0&
0"
#60
1!
1'
1.
15
13
1-
11
b100 9
1/
1(
16
1)
1&
1"
#70
0/
0(
06
0)
0&
0"
#80
b101 9
1/
1(
16
1)
1&
1"
#90
0/
0(
06
0)
0&
0"
#100
b110 9
1/
1(
16
1)
1&
1"
#110
0/
0(
06
0)
0&
0"
#120
b111 9
1/
1(
16
1)
1&
1"
#130
0/
0(
06
0)
0&
0"
#140
0!
0'
0.
05
04
0,
08
1/
1(
16
1)
1&
1"
#150
0/
0(
06
0)
0&
0"
#160
1/
1(
16
1)
1&
1"
#170
0/
0(
06
0)
0&
0"
#180
1/
1(
16
1)
1&
1"
#190
0/
0(
06
0)
0&
0"
#200
b0 2
b0 9
1/
1(
16
1)
1&
1"
10
1*
17
1+
1%
1#
#210
0/
0(
06
0)
0&
0"
#220
03
0-
01
14
1,
18
b1 2
b1 9
1/
1(
16
1)
1&
1"
00
0*
07
0+
0%
0#
#230
0/
0(
06
0)
0&
0"
#240
b10 2
b10 9
1/
1(
16
1)
1&
1"
#250
0/
0(
06
0)
0&
0"
#260
b11 2
b11 9
1/
1(
16
1)
1&
1"
#270
0/
0(
06
0)
0&
0"
#280
1!
1'
1.
15
13
1-
11
b100 9
1/
1(
16
1)
1&
1"
#290
0/
0(
06
0)
0&
0"
#300
b101 9
1/
1(
16
1)
1&
1"
#310
0/
0(
06
0)
0&
0"
#320
b110 9
1/
1(
16
1)
1&
1"
#330
0/
0(
06
0)
0&
0"
#340
b111 9
1/
1(
16
1)
1&
1"
#350
0/
0(
06
0)
0&
0"
#360
0!
0'
0.
05
04
0,
08
1/
1(
16
1)
1&
1"
#370
0/
0(
06
0)
0&
0"
#380
1/
1(
16
1)
1&
1"
#390
0/
0(
06
0)
0&
0"
#400
1/
1(
16
1)
1&
1"
#410
0/
0(
06
0)
0&
0"
10
1*
17
1+
1%
1#
#420
b0 2
b0 9
1/
1(
16
1)
1&
1"
#430
0/
0(
06
0)
0&
0"
00
0*
07
0+
0%
0#
#440
03
0-
01
14
1,
18
b1 2
b1 9
1/
1(
16
1)
1&
1"
#450
0/
0(
06
0)
0&
0"
#460
b10 2
b10 9
1/
1(
16
1)
1&
1"
#470
0/
0(
06
0)
0&
0"
#480
b11 2
b11 9
1/
1(
16
1)
1&
1"
#490
0/
0(
06
0)
0&
0"
#500
1!
1'
1.
15
13
1-
11
b100 9
1/
1(
16
1)
1&
1"
#510
0/
0(
06
0)
0&
0"
#520
b101 9
1/
1(
16
1)
1&
1"
#530
0/
0(
06
0)
0&
0"
#540
b110 9
1/
1(
16
1)
1&
1"
#550
0/
0(
06
0)
0&
0"
#560
b111 9
1/
1(
16
1)
1&
1"
#570
0/
0(
06
0)
0&
0"
#580
0!
0'
0.
05
04
0,
08
1/
1(
16
1)
1&
1"
#590
0/
0(
06
0)
0&
0"
#600
1/
1(
16
1)
1&
1"
#610
0/
0(
06
0)
0&
0"
#620
1/
1(
16
1)
1&
1"
#630
0/
0(
06
0)
0&
0"
#640
b0 2
b0 9
1/
1(
16
1)
1&
1"
10
1*
17
1+
1%
1#
#650
0/
0(
06
0)
0&
0"
#660
03
0-
01
14
1,
18
b1 2
b1 9
1/
1(
16
1)
1&
1"
00
0*
07
0+
0%
0#
#670
0/
0(
06
0)
0&
0"
#680
b10 2
b10 9
1/
1(
16
1)
1&
1"
#690
0/
0(
06
0)
0&
0"
#700
b11 2
b11 9
1/
1(
16
1)
1&
1"
#710
0/
0(
06
0)
0&
0"
#720
1!
1'
1.
15
13
1-
11
b100 9
1/
1(
16
1)
1&
1"
#730
0/
0(
06
0)
0&
0"
#740
b101 9
1/
1(
16
1)
1&
1"
#750
0/
0(
06
0)
0&
0"
#760
b110 9
1/
1(
16
1)
1&
1"
#770
0/
0(
06
0)
0&
0"
#780
b111 9
1/
1(
16
1)
1&
1"
#790
0/
0(
06
0)
0&
0"
#800
0!
0'
0.
05
04
0,
08
1/
1(
16
1)
1&
1"
#810
0/
0(
06
0)
0&
0"
#820
1/
1(
16
1)
1&
1"
#830
0/
0(
06
0)
0&
0"
#840
1/
1(
16
1)
1&
1"
#850
0/
0(
06
0)
0&
0"
#860
1/
1(
16
1)
1&
1"
#870
0/
0(
06
0)
0&
0"
#880
1/
1(
16
1)
1&
1"
#890
0/
0(
06
0)
0&
0"
#900
1/
1(
16
1)
1&
1"
#910
0/
0(
06
0)
0&
0"
#920
1/
1(
16
1)
1&
1"
#930
0/
0(
06
0)
0&
0"
#940
1/
1(
16
1)
1&
1"
#950
0/
0(
06
0)
0&
0"
#960
1/
1(
16
1)
1&
1"
#970
0/
0(
06
0)
0&
0"
#980
1/
1(
16
1)
1&
1"
#990
0/
0(
06
0)
0&
0"
#1000
1/
1(
16
1)
1&
1"
#1010
0/
0(
06
0)
0&
0"
#1020
1/
1(
16
1)
1&
1"
#1030
0/
0(
06
0)
0&
0"
#1040
1/
1(
16
1)
1&
1"
#1050
0/
0(
06
0)
0&
0"
#1060
1/
1(
16
1)
1&
1"
#1070
0/
0(
06
0)
0&
0"
#1080
1/
1(
16
1)
1&
1"
#1090
0/
0(
06
0)
0&
0"
#1100
1/
1(
16
1)
1&
1"
#1110
0/
0(
06
0)
0&
0"
#1120
1/
1(
16
1)
1&
1"
#1130
0/
0(
06
0)
0&
0"
#1140
1/
1(
16
1)
1&
1"
#1150
0/
0(
06
0)
0&
0"
#1160
1/
1(
16
1)
1&
1"
#1170
0/
0(
06
0)
0&
0"
#1180
1/
1(
16
1)
1&
1"
#1190
0/
0(
06
0)
0&
0"
#1200
1/
1(
16
1)
1&
1"
#1210
0/
0(
06
0)
0&
0"
#1220
1/
1(
16
1)
1&
1"
#1230
0/
0(
06
0)
0&
0"
#1240
1/
1(
16
1)
1&
1"
#1250
0/
0(
06
0)
0&
0"
#1260
1/
1(
16
1)
1&
1"
#1270
0/
0(
06
0)
0&
0"
#1280
1/
1(
16
1)
1&
1"
#1290
0/
0(
06
0)
0&
0"
#1300
1/
1(
16
1)
1&
1"
#1310
0/
0(
06
0)
0&
0"
#1320
1/
1(
16
1)
1&
1"
#1330
0/
0(
06
0)
0&
0"
#1340
1/
1(
16
1)
1&
1"
#1350
0/
0(
06
0)
0&
0"
#1360
1/
1(
16
1)
1&
1"
#1370
0/
0(
06
0)
0&
0"
#1380
1/
1(
16
1)
1&
1"
#1390
0/
0(
06
0)
0&
0"
#1400
1/
1(
16
1)
1&
1"
#1410
0/
0(
06
0)
0&
0"
#1420
1/
1(
16
1)
1&
1"
#1430
0/
0(
06
0)
0&
0"
#1440
1/
1(
16
1)
1&
1"
#1450
0/
0(
06
0)
0&
0"
#1460
1/
1(
16
1)
1&
1"
#1470
0/
0(
06
0)
0&
0"
#1480
1/
1(
16
1)
1&
1"
#1490
0/
0(
06
0)
0&
0"
#1500
1/
1(
16
1)
1&
1"
#1510
0/
0(
06
0)
0&
0"
#1520
1/
1(
16
1)
1&
1"
#1530
0/
0(
06
0)
0&
0"
#1540
1/
1(
16
1)
1&
1"
#1550
0/
0(
06
0)
0&
0"
#1560
1/
1(
16
1)
1&
1"
#1570
0/
0(
06
0)
0&
0"
#1580
1/
1(
16
1)
1&
1"
#1590
0/
0(
06
0)
0&
0"
#1600
1/
1(
16
1)
1&
1"
#1610
0/
0(
06
0)
0&
0"
#1620
1/
1(
16
1)
1&
1"
#1630
0/
0(
06
0)
0&
0"
#1640
1/
1(
16
1)
1&
1"
#1650
0/
0(
06
0)
0&
0"
#1660
1/
1(
16
1)
1&
1"
